<?xml version="1.0" encoding="UTF-8"?>
    <root>
        <he index="0" x="255.75" y="832.0"/>
        <he index="1" x="407.25" y="1353.0"/>
        <he index="2" x="585.75" y="63.5"/>
        <he index="3" x="514.25" y="154.5"/>
        <he index="4" x="765.75" y="1042.5"/>
        <he index="5" x="672.25" y="168.0"/>
        <he index="6" x="301.25" y="32.5"/>
        <he index="7" x="158.25" y="259.0"/>
        <he index="8" x="697.75" y="569.0"/>
        <he index="9" x="108.25" y="107.5"/>
        <he index="10" x="531.75" y="445.0"/>
        <he index="11" x="924.25" y="94.5"/>
        <he index="12" x="762.25" y="628.5"/>
        <he index="13" x="974.25" y="580.5"/>
        <he index="14" x="473.25" y="648.0"/>
        <he index="15" x="116.75" y="1207.5"/>
        <he index="16" x="203.25" y="1277.0"/>
        <he index="17" x="569.25" y="152.5"/>
        <he index="18" x="797.75" y="82.0"/>
        <he index="19" x="528.25" y="970.0"/>
        <he index="20" x="258.25" y="28.5"/>
        <he index="21" x="717.75" y="493.5"/>
        <he index="22" x="62.25" y="603.5"/>
        <he index="23" x="438.75" y="536.5"/>
        <he index="24" x="720.25" y="1169.5"/>
        <he index="25" x="177.25" y="826.5"/>
        <he index="26" x="429.75" y="1429.5"/>
        <he index="27" x="494.75" y="603.5"/>
        <he index="28" x="81.75" y="866.0"/>
        <he index="29" x="191.25" y="1198.0"/>
        <he index="30" x="503.75" y="271.5"/>
        <he index="31" x="550.75" y="62.5"/>
        <he index="32" x="722.25" y="397.0"/>
        <he index="33" x="484.75" y="231.0"/>
        <he index="34" x="444.25" y="302.0"/>
        <he index="35" x="311.75" y="1029.0"/>
        <he index="36" x="409.75" y="1310.5"/>
        <he index="37" x="422.25" y="682.0"/>
        <he index="38" x="332.75" y="277.0"/>
        <he index="39" x="339.75" y="1123.5"/>
        <he index="40" x="308.75" y="373.0"/>
        <he index="41" x="900.75" y="532.5"/>
        <he index="42" x="1009.25" y="674.5"/>
        <he index="43" x="788.25" y="732.0"/>
        <he index="44" x="447.25" y="639.5"/>
        <he index="45" x="518.25" y="1400.0"/>
        <he index="46" x="60.25" y="568.0"/>
        <he index="47" x="237.75" y="188.5"/>
        <he index="48" x="541.25" y="359.0"/>
        <he index="49" x="436.25" y="1217.5"/>
        <he index="50" x="484.25" y="366.0"/>
        <he index="51" x="222.75" y="545.5"/>
        <he index="52" x="351.25" y="288.5"/>
        <he index="53" x="1074.75" y="27.0"/>
        <he index="54" x="925.25" y="422.5"/>
        <he index="55" x="770.25" y="406.5"/>
        <he index="56" x="178.75" y="297.0"/>
        <he index="57" x="904.75" y="684.0"/>
        <he index="58" x="526.75" y="1004.0"/>
        <he index="59" x="814.75" y="505.5"/>
        <he index="60" x="385.75" y="1234.5"/>
        <he index="61" x="709.25" y="885.0"/>
        <he index="62" x="358.25" y="1284.0"/>
        <he index="63" x="272.75" y="1070.0"/>
        <he index="64" x="711.25" y="1267.0"/>
        <he index="65" x="98.75" y="169.0"/>
        <he index="66" x="736.75" y="964.5"/>
        <he index="67" x="330.75" y="609.0"/>
        <he index="68" x="1061.25" y="589.0"/>
        <he index="69" x="813.75" y="900.5"/>
        <he index="70" x="155.25" y="209.0"/>
        <he index="71" x="713.75" y="548.5"/>
        <he index="72" x="264.25" y="1102.0"/>
        <he index="73" x="862.75" y="118.0"/>
        <he index="74" x="452.25" y="1506.0"/>
        <he index="75" x="432.25" y="1134.0"/>
        <he index="76" x="291.25" y="349.0"/>
        <he index="77" x="975.25" y="288.5"/>
        <he index="78" x="470.75" y="1031.5"/>
        <he index="79" x="756.75" y="1098.0"/>
        <he index="80" x="433.75" y="1386.5"/>
        <he index="81" x="729.25" y="527.5"/>
        <he index="82" x="113.75" y="470.0"/>
        <he index="83" x="830.75" y="346.5"/>
        <he index="84" x="235.75" y="578.0"/>
        <he index="85" x="789.75" y="641.0"/>
        <he index="86" x="260.25" y="1550.5"/>
        <he index="87" x="483.25" y="895.0"/>
        <he index="88" x="531.25" y="935.0"/>
        <he index="89" x="157.25" y="856.0"/>
        <he index="90" x="581.25" y="939.5"/>
        <he index="91" x="127.75" y="636.0"/>
        <he index="92" x="132.25" y="860.0"/>
        <he index="93" x="826.75" y="179.0"/>
        <he index="94" x="396.25" y="388.0"/>
        <he index="95" x="31.25" y="570.0"/>
        <he index="96" x="31.25" y="535.0"/>
        <he index="97" x="121.25" y="504.5"/>
        <he index="98" x="653.75" y="660.5"/>
        <he index="99" x="31.25" y="735.0"/>
        <he index="100" x="380.75" y="206.0"/>
        <he index="101" x="38.25" y="300.5"/>
        <he index="102" x="571.25" y="19.5"/>
        <he index="103" x="444.25" y="414.0"/>
        <he index="104" x="416.75" y="797.5"/>
        <he index="105" x="637.25" y="1394.0"/>
        <he index="106" x="65.75" y="479.0"/>
        <he index="107" x="31.25" y="605.5"/>
        <he index="108" x="753.25" y="1002.0"/>
        <he index="109" x="706.75" y="106.5"/>
        <he index="110" x="745.25" y="450.5"/>
        <he index="111" x="103.75" y="640.5"/>
        <he index="112" x="528.75" y="218.5"/>
        <he index="113" x="31.25" y="1103.5"/>
        <he index="114" x="151.25" y="1163.5"/>
        <he index="115" x="337.25" y="1165.5"/>
        <he index="116" x="514.75" y="1230.0"/>
        <he index="117" x="138.75" y="518.0"/>
        <he index="118" x="31.25" y="647.5"/>
        <he index="119" x="519.25" y="314.5"/>
        <he index="120" x="974.25" y="521.0"/>
        <he index="121" x="573.75" y="731.0"/>
        <he index="122" x="215.75" y="1194.0"/>
        <he index="123" x="891.75" y="121.0"/>
        <he index="124" x="915.25" y="507.0"/>
        <he index="125" x="505.25" y="949.5"/>
        <he index="126" x="814.25" y="1203.5"/>
        <he index="127" x="404.75" y="1395.0"/>
        <he index="128" x="820.25" y="370.5"/>
        <he index="129" x="263.25" y="734.0"/>
        <he index="130" x="945.75" y="285.5"/>
        <he index="131" x="679.25" y="676.5"/>
        <he index="132" x="388.25" y="236.5"/>
        <he index="133" x="812.75" y="561.5"/>
        <he index="134" x="695.75" y="1184.0"/>
        <he index="135" x="380.75" y="155.5"/>
        <he index="136" x="680.75" y="282.0"/>
        <he index="137" x="100.25" y="192.5"/>
        <he index="138" x="341.75" y="725.5"/>
        <he index="139" x="245.75" y="244.5"/>
        <he index="140" x="936.75" y="203.0"/>
        <he index="141" x="31.25" y="1045.5"/>
        <he index="142" x="960.25" y="231.5"/>
        <he index="143" x="31.25" y="986.5"/>
        <he index="144" x="712.75" y="725.5"/>
        <he index="145" x="859.75" y="1071.0"/>
        <he index="146" x="1016.25" y="35.0"/>
        <he index="147" x="854.75" y="434.0"/>
        <he index="148" x="271.75" y="1508.0"/>
        <he index="149" x="643.25" y="88.0"/>
        <he index="150" x="308.25" y="158.5"/>
        <he index="151" x="652.25" y="818.0"/>
        <he index="152" x="439.75" y="818.5"/>
        <he index="153" x="180.75" y="345.5"/>
        <he index="154" x="632.25" y="906.0"/>
        <he index="155" x="726.25" y="1395.0"/>
        <he index="156" x="484.75" y="758.5"/>
        <he index="157" x="840.25" y="1329.5"/>
        <he index="158" x="190.75" y="643.0"/>
        <he index="159" x="332.25" y="930.0"/>
        <he index="160" x="399.25" y="619.0"/>
        <he index="161" x="139.75" y="269.5"/>
        <he index="162" x="93.75" y="818.0"/>
        <he index="163" x="155.25" y="1484.5"/>
        <he index="164" x="400.25" y="433.0"/>
        <he index="165" x="31.25" y="778.5"/>
        <he index="166" x="31.25" y="500.0"/>
        <he index="167" x="980.75" y="715.5"/>
        <he index="168" x="831.25" y="829.0"/>
        <he index="169" x="307.75" y="596.5"/>
        <he index="170" x="744.25" y="506.5"/>
        <he index="171" x="122.25" y="437.5"/>
        <he index="172" x="392.25" y="284.5"/>
        <he index="173" x="926.75" y="720.5"/>
        <he index="174" x="101.25" y="376.0"/>
        <he index="175" x="946.75" y="149.0"/>
        <he index="176" x="420.75" y="1515.0"/>
        <he index="177" x="767.75" y="753.5"/>
        <he index="178" x="362.75" y="1199.5"/>
        <he index="179" x="626.25" y="428.5"/>
        <he index="180" x="695.75" y="399.5"/>
        <he index="181" x="810.75" y="241.5"/>
        <he index="182" x="711.25" y="1032.5"/>
        <he index="183" x="200.25" y="359.0"/>
        <he index="184" x="452.75" y="216.5"/>
        <he index="185" x="31.25" y="928.0"/>
        <he index="186" x="599.75" y="428.0"/>
        <he index="187" x="86.75" y="730.5"/>
        <he index="188" x="696.75" y="994.0"/>
        <he index="189" x="31.25" y="1492.0"/>
        <he index="190" x="772.25" y="462.5"/>
        <he index="191" x="907.25" y="390.5"/>
        <he index="192" x="690.25" y="186.0"/>
        <he index="193" x="647.25" y="178.0"/>
        <he index="194" x="1044.75" y="441.5"/>
        <he index="195" x="197.75" y="877.5"/>
        <he index="196" x="372.25" y="532.0"/>
        <he index="197" x="186.25" y="1481.0"/>
        <he index="198" x="566.75" y="317.5"/>
        <he index="199" x="206.75" y="1397.5"/>
        <he index="200" x="89.75" y="1042.0"/>
        <he index="201" x="294.75" y="1094.5"/>
        <he index="202" x="187.25" y="1360.0"/>
        <he index="203" x="623.25" y="249.5"/>
        <he index="204" x="215.75" y="1355.5"/>
        <he index="205" x="205.25" y="1025.5"/>
        <he index="206" x="270.25" y="310.5"/>
        <he index="207" x="471.25" y="622.0"/>
        <he index="208" x="783.25" y="172.5"/>
        <he index="209" x="31.25" y="691.5"/>
        <he index="210" x="447.25" y="436.0"/>
        <he index="211" x="923.75" y="256.0"/>
        <he index="212" x="243.75" y="91.0"/>
        <he index="213" x="1043.25" y="538.0"/>
        <he index="214" x="597.75" y="599.0"/>
        <he index="215" x="645.75" y="476.5"/>
        <he index="216" x="74.25" y="1370.5"/>
        <he index="217" x="227.75" y="768.5"/>
        <he index="218" x="491.75" y="577.5"/>
        <he index="219" x="653.25" y="153.5"/>
        <he index="220" x="733.25" y="66.5"/>
        <he index="221" x="177.25" y="692.0"/>
        <he index="222" x="721.25" y="149.0"/>
        <he index="223" x="17.75" y="432.0"/>
        <he index="224" x="714.25" y="26.0"/>
        <he index="225" x="531.75" y="1135.0"/>
        <he index="226" x="629.25" y="836.0"/>
        <he index="227" x="510.75" y="1188.0"/>
        <he index="228" x="459.25" y="154.5"/>
        <he index="229" x="590.75" y="1060.0"/>
        <he index="230" x="207.75" y="117.5"/>
        <he index="231" x="463.25" y="1250.0"/>
        <he index="232" x="360.75" y="1044.0"/>
        <he index="233" x="172.25" y="1120.0"/>
        <he index="234" x="751.25" y="1336.0"/>
        <he index="235" x="375.75" y="582.5"/>
        <he index="236" x="419.25" y="243.5"/>
        <he index="237" x="213.25" y="1083.5"/>
        <he index="238" x="496.25" y="206.0"/>
        <he index="239" x="554.25" y="338.5"/>
        <he index="240" x="79.25" y="1170.5"/>
        <he index="241" x="910.75" y="625.5"/>
        <he index="242" x="220.75" y="397.5"/>
        <he index="243" x="734.75" y="616.0"/>
        <he index="244" x="37.25" y="147.5"/>
        <he index="245" x="61.75" y="1102.0"/>
        <he index="246" x="841.25" y="572.0"/>
        <he index="247" x="262.25" y="103.0"/>
        <he index="248" x="901.25" y="226.0"/>
        <he index="249" x="773.25" y="789.0"/>
        <he index="250" x="943.75" y="574.5"/>
        <he index="251" x="176.25" y="247.0"/>
        <he index="252" x="115.25" y="130.5"/>
        <he index="253" x="212.75" y="42.0"/>
        <he index="254" x="576.25" y="1377.5"/>
        <he index="255" x="827.75" y="687.0"/>
        <he index="256" x="408.25" y="1100.5"/>
        <he index="257" x="250.75" y="1309.0"/>
        <he index="258" x="340.25" y="1020.0"/>
        <he index="259" x="123.75" y="594.0"/>
        <he index="260" x="565.75" y="361.5"/>
        <he index="261" x="274.75" y="62.0"/>
        <he index="262" x="312.75" y="1213.5"/>
        <he index="263" x="394.75" y="115.0"/>
        <he index="264" x="187.75" y="999.0"/>
        <he index="265" x="324.75" y="1538.5"/>
        <he index="266" x="243.75" y="141.5"/>
        <he index="267" x="150.75" y="698.0"/>
        <he index="268" x="160.25" y="307.5"/>
        <he index="269" x="684.75" y="904.0"/>
        <he index="270" x="438.25" y="119.0"/>
        <he index="271" x="484.25" y="1156.0"/>
        <he index="272" x="121.75" y="370.0"/>
        <he index="273" x="163.25" y="59.5"/>
        <he index="274" x="401.25" y="966.5"/>
        <he index="275" x="561.25" y="231.0"/>
        <he index="276" x="561.75" y="106.5"/>
        <he index="277" x="983.25" y="93.5"/>
        <he index="278" x="1037.75" y="703.5"/>
        <he index="279" x="264.25" y="256.5"/>
        <he index="280" x="760.25" y="894.5"/>
        <he index="281" x="417.25" y="179.5"/>
        <he index="282" x="47.25" y="1451.5"/>
        <he index="283" x="871.25" y="466.0"/>
        <he index="284" x="242.25" y="217.0"/>
        <he index="285" x="326.25" y="660.5"/>
        <he index="286" x="285.75" y="749.0"/>
        <he index="287" x="556.75" y="448.5"/>
        <he index="288" x="174.25" y="221.5"/>
        <he index="289" x="667.25" y="1424.0"/>
        <he index="290" x="301.25" y="790.0"/>
        <he index="291" x="92.25" y="1100.0"/>
        <he index="292" x="165.25" y="510.5"/>
        <he index="293" x="517.25" y="584.5"/>
        <he index="294" x="849.25" y="193.0"/>
        <he index="295" x="681.75" y="501.0"/>
        <he index="296" x="119.25" y="1407.5"/>
        <he index="297" x="565.25" y="662.5"/>
        <he index="298" x="182.25" y="851.0"/>
        <he index="299" x="716.75" y="636.5"/>
        <he index="300" x="217.25" y="1476.5"/>
        <he index="301" x="463.25" y="193.5"/>
        <he index="302" x="914.75" y="565.5"/>
        <he index="303" x="690.75" y="256.0"/>
        <he index="304" x="594.25" y="714.5"/>
        <he index="305" x="114.25" y="727.0"/>
        <he index="306" x="616.75" y="97.0"/>
        <he index="307" x="435.25" y="1344.0"/>
        <he index="308" x="57.25" y="689.5"/>
        <he index="309" x="438.25" y="368.0"/>
        <he index="310" x="324.75" y="513.0"/>
        <he index="311" x="362.75" y="1116.0"/>
        <he index="312" x="661.25" y="1338.5"/>
        <he index="313" x="271.75" y="1345.5"/>
        <he index="314" x="763.25" y="1236.5"/>
        <he index="315" x="397.25" y="568.0"/>
        <he index="316" x="458.75" y="519.5"/>
        <he index="317" x="966.75" y="316.0"/>
        <he index="318" x="625.75" y="1267.0"/>
        <he index="319" x="957.25" y="343.0"/>
        <he index="320" x="384.25" y="323.0"/>
        <he index="321" x="208.25" y="1518.0"/>
        <he index="322" x="801.25" y="192.5"/>
        <he index="323" x="332.75" y="421.5"/>
        <he index="324" x="334.25" y="201.0"/>
        <he index="325" x="247.75" y="1472.0"/>
        <he index="326" x="309.25" y="460.0"/>
        <he index="327" x="31.25" y="822.5"/>
        <he index="328" x="132.75" y="74.5"/>
        <he index="329" x="398.25" y="410.5"/>
        <he index="330" x="670.75" y="354.5"/>
        <he index="331" x="525.75" y="694.5"/>
        <he index="332" x="140.25" y="293.0"/>
        <he index="333" x="466.25" y="131.0"/>
        <he index="334" x="796.25" y="862.5"/>
        <he index="335" x="74.25" y="1013.5"/>
        <he index="336" x="243.25" y="1077.0"/>
        <he index="337" x="446.75" y="613.0"/>
        <he index="338" x="746.25" y="774.5"/>
        <he index="339" x="670.25" y="28.5"/>
        <he index="340" x="198.25" y="618.0"/>
        <he index="341" x="568.75" y="1072.0"/>
        <he index="342" x="528.25" y="513.5"/>
        <he index="343" x="745.75" y="138.0"/>
        <he index="344" x="269.25" y="83.0"/>
        <he index="345" x="442.25" y="390.0"/>
        <he index="346" x="480.75" y="929.5"/>
        <he index="347" x="385.75" y="1108.5"/>
        <he index="348" x="898.75" y="43.5"/>
        <he index="349" x="59.25" y="297.0"/>
        <he index="350" x="179.75" y="941.0"/>
        <he index="351" x="491.25" y="1367.0"/>
        <he index="352" x="151.75" y="631.0"/>
        <he index="353" x="655.25" y="1022.0"/>
        <he index="354" x="750.75" y="213.0"/>
        <he index="355" x="384.25" y="909.5"/>
        <he index="356" x="480.75" y="59.5"/>
        <he index="357" x="121.75" y="415.0"/>
        <he index="358" x="217.25" y="794.5"/>
        <he index="359" x="855.75" y="699.0"/>
        <he index="360" x="428.25" y="324.0"/>
        <he index="361" x="396.75" y="1480.5"/>
        <he index="362" x="169.25" y="168.5"/>
        <he index="363" x="553.25" y="34.0"/>
        <he index="364" x="742.25" y="241.5"/>
        <he index="365" x="183.25" y="523.0"/>
        <he index="366" x="501.25" y="984.5"/>
        <he index="367" x="455.25" y="1125.0"/>
        <he index="368" x="335.75" y="151.0"/>
        <he index="369" x="107.75" y="1448.5"/>
        <he index="370" x="209.25" y="220.0"/>
        <he index="371" x="271.25" y="980.0"/>
        <he index="372" x="154.75" y="79.5"/>
        <he index="373" x="259.75" y="642.0"/>
        <he index="374" x="657.75" y="1295.5"/>
        <he index="375" x="375.25" y="634.0"/>
        <he index="376" x="180.25" y="121.5"/>
        <he index="377" x="709.75" y="324.5"/>
        <he index="378" x="887.75" y="147.0"/>
        <he index="379" x="360.75" y="765.0"/>
        <he index="380" x="813.25" y="131.0"/>
        <he index="381" x="375.75" y="477.0"/>
        <he index="382" x="67.25" y="667.0"/>
        <he index="383" x="196.25" y="1318.5"/>
        <he index="384" x="898.75" y="334.0"/>
        <he index="385" x="786.75" y="494.5"/>
        <he index="386" x="836.75" y="242.0"/>
        <he index="387" x="543.25" y="1261.0"/>
        <he index="388" x="989.75" y="553.5"/>
        <he index="389" x="423.25" y="629.5"/>
        <he index="390" x="1036.25" y="632.5"/>
        <he index="391" x="79.75" y="270.0"/>
        <he index="392" x="172.25" y="92.0"/>
        <he index="393" x="396.25" y="999.5"/>
        <he index="394" x="266.75" y="592.0"/>
        <he index="395" x="296.75" y="253.0"/>
        <he index="396" x="608.25" y="663.5"/>
        <he index="397" x="179.75" y="321.0"/>
        <he index="398" x="432.25" y="920.5"/>
        <he index="399" x="735.25" y="38.5"/>
        <he index="400" x="792.75" y="361.0"/>
        <he index="401" x="712.75" y="53.0"/>
        <he index="402" x="589.25" y="405.5"/>
        <he index="403" x="802.75" y="337.5"/>
        <he index="404" x="492.25" y="96.0"/>
        <he index="405" x="850.25" y="866.5"/>
        <he index="406" x="16.75" y="345.5"/>
        <he index="407" x="639.75" y="714.0"/>
        <he index="408" x="663.25" y="1156.5"/>
        <he index="409" x="375.75" y="103.0"/>
        <he index="410" x="125.25" y="813.5"/>
        <he index="411" x="270.75" y="801.0"/>
        <he index="412" x="490.75" y="1282.5"/>
        <he index="413" x="808.25" y="1010.0"/>
        <he index="414" x="779.25" y="1320.0"/>
        <he index="415" x="680.75" y="589.0"/>
        <he index="416" x="330.75" y="466.5"/>
        <he index="417" x="632.25" y="226.0"/>
        <he index="418" x="337.25" y="78.5"/>
        <he index="419" x="264.75" y="1387.5"/>
        <he index="420" x="613.25" y="550.5"/>
        <he index="421" x="172.75" y="17.0"/>
        <he index="422" x="433.75" y="346.0"/>
        <he index="423" x="419.25" y="107.0"/>
        <he index="424" x="822.75" y="37.0"/>
        <he index="425" x="121.25" y="324.5"/>
        <he index="426" x="199.25" y="335.0"/>
        <he index="427" x="751.25" y="810.0"/>
        <he index="428" x="686.75" y="91.0"/>
        <he index="429" x="287.75" y="95.0"/>
        <he index="430" x="436.25" y="1175.0"/>
        <he index="431" x="736.75" y="369.5"/>
        <he index="432" x="81.25" y="618.5"/>
        <he index="433" x="100.75" y="331.5"/>
        <he index="434" x="775.75" y="933.5"/>
        <he index="435" x="38.75" y="213.0"/>
        <he index="436" x="486.75" y="121.0"/>
        <he index="437" x="466.75" y="300.0"/>
        <he index="438" x="508.75" y="812.5"/>
        <he index="439" x="866.75" y="409.5"/>
        <he index="440" x="337.75" y="897.0"/>
        <he index="441" x="388.75" y="345.0"/>
        <he index="442" x="535.25" y="145.5"/>
        <he index="443" x="926.75" y="68.0"/>
        <he index="444" x="283.75" y="632.0"/>
        <he index="445" x="1054.25" y="516.5"/>
        <he index="446" x="733.25" y="865.0"/>
        <he index="447" x="541.75" y="118.0"/>
        <he index="448" x="809.25" y="394.0"/>
        <he index="449" x="871.75" y="223.0"/>
        <he index="450" x="532.75" y="866.0"/>
        <he index="451" x="235.75" y="1393.0"/>
        <he index="452" x="55.25" y="1172.0"/>
        <he index="453" x="441.25" y="750.5"/>
        <he index="454" x="257.25" y="375.0"/>
        <he index="455" x="375.75" y="1403.5"/>
        <he index="456" x="982.75" y="642.0"/>
        <he index="457" x="580.75" y="835.0"/>
        <he index="458" x="329.25" y="489.0"/>
        <he index="459" x="865.25" y="248.5"/>
        <he index="460" x="49.25" y="843.5"/>
        <he index="461" x="678.25" y="142.5"/>
        <he index="462" x="554.25" y="782.0"/>
        <he index="463" x="304.25" y="308.0"/>
        <he index="464" x="159.75" y="741.0"/>
        <he index="465" x="643.25" y="312.0"/>
        <he index="466" x="869.75" y="327.5"/>
        <he index="467" x="526.75" y="335.5"/>
        <he index="468" x="177.75" y="1401.5"/>
        <he index="469" x="59.25" y="341.0"/>
        <he index="470" x="60.75" y="777.0"/>
        <he index="471" x="256.75" y="759.5"/>
        <he index="472" x="551.75" y="382.5"/>
        <he index="473" x="462.75" y="236.5"/>
        <he index="474" x="257.75" y="1429.5"/>
        <he index="475" x="794.25" y="970.0"/>
        <he index="476" x="298.25" y="53.5"/>
        <he index="477" x="175.25" y="599.0"/>
        <he index="478" x="215.75" y="298.5"/>
        <he index="479" x="826.75" y="1146.0"/>
        <he index="480" x="845.25" y="756.0"/>
        <he index="481" x="633.75" y="1035.0"/>
        <he index="482" x="441.75" y="562.0"/>
        <he index="483" x="716.75" y="979.5"/>
        <he index="484" x="996.25" y="405.5"/>
        <he index="485" x="783.75" y="1363.5"/>
        <he index="486" x="917.25" y="147.5"/>
        <he index="487" x="134.75" y="1245.5"/>
        <he index="488" x="205.75" y="589.5"/>
        <he index="489" x="262.75" y="1012.5"/>
        <he index="490" x="781.75" y="384.0"/>
        <he index="491" x="43.75" y="1292.0"/>
        <he index="492" x="38.25" y="257.0"/>
        <he index="493" x="136.25" y="196.0"/>
        <he index="494" x="131.25" y="1008.0"/>
        <he index="495" x="300.75" y="280.5"/>
        <he index="496" x="131.25" y="484.0"/>
        <he index="497" x="777.25" y="67.5"/>
        <he index="498" x="177.75" y="272.0"/>
        <he index="499" x="292.75" y="881.5"/>
        <he index="500" x="469.25" y="412.5"/>
        <he index="501" x="629.25" y="160.0"/>
        <he index="502" x="619.25" y="732.0"/>
        <he index="503" x="182.75" y="416.0"/>
        <he index="504" x="757.25" y="539.0"/>
        <he index="505" x="353.25" y="596.0"/>
        <he index="506" x="234.25" y="1019.5"/>
        <he index="507" x="186.75" y="802.0"/>
        <he index="508" x="117.25" y="660.5"/>
        <he index="509" x="166.75" y="1201.5"/>
        <he index="510" x="235.75" y="501.5"/>
        <he index="511" x="176.75" y="1522.0"/>
        <he index="512" x="322.25" y="1375.5"/>
        <he index="513" x="99.25" y="217.0"/>
        <he index="514" x="352.25" y="212.5"/>
        <he index="515" x="472.25" y="675.5"/>
        <he index="516" x="779.75" y="697.5"/>
        <he index="517" x="532.75" y="831.5"/>
        <he index="518" x="80.75" y="381.0"/>
        <he index="519" x="244.25" y="601.5"/>
        <he index="520" x="327.25" y="357.0"/>
        <he index="521" x="799.75" y="528.5"/>
        <he index="522" x="751.75" y="594.5"/>
        <he index="523" x="599.25" y="1279.5"/>
        <he index="524" x="373.75" y="977.0"/>
        <he index="525" x="878.25" y="384.5"/>
        <he index="526" x="623.25" y="183.5"/>
        <he index="527" x="58.75" y="1331.5"/>
        <he index="528" x="1025.75" y="410.5"/>
        <he index="529" x="206.75" y="935.5"/>
        <he index="530" x="349.75" y="360.0"/>
        <he index="531" x="821.25" y="290.5"/>
        <he index="532" x="226.25" y="448.0"/>
        <he index="533" x="85.25" y="529.5"/>
        <he index="534" x="849.25" y="298.0"/>
        <he index="535" x="169.25" y="38.5"/>
        <he index="536" x="820.75" y="68.5"/>
        <he index="537" x="624.25" y="994.0"/>
        <he index="538" x="80.75" y="403.0"/>
        <he index="539" x="813.75" y="448.5"/>
        <he index="540" x="220.75" y="470.0"/>
        <he index="541" x="883.25" y="172.5"/>
        <he index="542" x="137.75" y="221.0"/>
        <he index="543" x="203.25" y="1115.0"/>
        <he index="544" x="146.75" y="887.5"/>
        <he index="545" x="852.75" y="919.0"/>
        <he index="546" x="806.75" y="1303.5"/>
        <he index="547" x="424.25" y="458.5"/>
        <he index="548" x="644.75" y="981.0"/>
        <he index="549" x="721.75" y="297.0"/>
        <he index="550" x="168.75" y="1322.0"/>
        <he index="551" x="422.75" y="656.0"/>
        <he index="552" x="602.75" y="295.5"/>
        <he index="553" x="408.75" y="1142.5"/>
        <he index="554" x="376.75" y="430.5"/>
        <he index="555" x="38.25" y="452.0"/>
        <he index="556" x="181.25" y="369.0"/>
        <he index="557" x="462.75" y="1377.0"/>
        <he index="558" x="290.25" y="146.5"/>
        <he index="559" x="463.75" y="1292.5"/>
        <he index="560" x="703.75" y="939.5"/>
        <he index="561" x="605.75" y="337.5"/>
        <he index="562" x="995.75" y="622.0"/>
        <he index="563" x="912.75" y="174.0"/>
        <he index="564" x="627.25" y="645.5"/>
        <he index="565" x="942.25" y="455.0"/>
        <he index="566" x="907.75" y="308.0"/>
        <he index="567" x="418.75" y="390.0"/>
        <he index="568" x="187.75" y="734.5"/>
        <he index="569" x="282.25" y="1262.0"/>
        <he index="570" x="458.25" y="1462.5"/>
        <he index="571" x="38.25" y="278.5"/>
        <he index="572" x="240.25" y="1189.0"/>
        <he index="573" x="578.25" y="382.0"/>
        <he index="574" x="216.25" y="491.0"/>
        <he index="575" x="350.75" y="1368.5"/>
        <he index="576" x="142.75" y="431.5"/>
        <he index="577" x="375.25" y="499.5"/>
        <he index="578" x="79.75" y="643.5"/>
        <he index="579" x="930.25" y="540.0"/>
        <he index="580" x="120.75" y="891.5"/>
        <he index="581" x="748.25" y="289.5"/>
        <he index="582" x="80.25" y="314.5"/>
        <he index="583" x="687.75" y="534.5"/>
        <he index="584" x="48.25" y="1132.0"/>
        <he index="585" x="635.75" y="452.5"/>
        <he index="586" x="196.25" y="709.5"/>
        <he index="587" x="527.75" y="729.0"/>
        <he index="588" x="555.25" y="1124.0"/>
        <he index="589" x="463.25" y="805.5"/>
        <he index="590" x="506.25" y="744.0"/>
        <he index="591" x="856.75" y="548.0"/>
        <he index="592" x="578.25" y="296.0"/>
        <he index="593" x="671.25" y="1198.0"/>
        <he index="594" x="313.25" y="1172.0"/>
        <he index="595" x="581.75" y="870.0"/>
        <he index="596" x="808.25" y="709.5"/>
        <he index="597" x="882.25" y="615.5"/>
        <he index="598" x="354.25" y="1077.0"/>
        <he index="599" x="205.75" y="438.0"/>
        <he index="600" x="539.25" y="191.5"/>
        <he index="601" x="630.75" y="1129.0"/>
        <he index="602" x="244.25" y="458.0"/>
        <he index="603" x="362.25" y="143.5"/>
        <he index="604" x="591.75" y="474.5"/>
        <he index="605" x="857.75" y="273.0"/>
        <he index="606" x="264.75" y="1184.0"/>
        <he index="607" x="327.25" y="1333.5"/>
        <he index="608" x="122.75" y="1097.0"/>
        <he index="609" x="521.25" y="610.0"/>
        <he index="610" x="70.75" y="710.5"/>
        <he index="611" x="888.75" y="359.5"/>
        <he index="612" x="521.25" y="489.5"/>
        <he index="613" x="478.75" y="1115.0"/>
        <he index="614" x="348.75" y="518.0"/>
        <he index="615" x="1032.25" y="470.0"/>
        <he index="616" x="327.75" y="806.5"/>
        <he index="617" x="450.75" y="323.0"/>
        <he index="618" x="304.75" y="1297.5"/>
        <he index="619" x="76.75" y="1072.0"/>
        <he index="620" x="123.75" y="1287.0"/>
        <he index="621" x="753.75" y="1195.5"/>
        <he index="622" x="796.75" y="584.5"/>
        <he index="623" x="306.75" y="107.0"/>
        <he index="624" x="100.75" y="308.5"/>
        <he index="625" x="789.25" y="142.5"/>
        <he index="626" x="484.25" y="723.5"/>
        <he index="627" x="321.75" y="535.0"/>
        <he index="628" x="659.75" y="695.5"/>
        <he index="629" x="160.75" y="456.5"/>
        <he index="630" x="574.25" y="621.0"/>
        <he index="631" x="113.75" y="1328.0"/>
        <he index="632" x="411.25" y="1268.0"/>
        <he index="633" x="267.25" y="445.0"/>
        <he index="634" x="405.75" y="324.5"/>
        <he index="635" x="189.75" y="909.0"/>
        <he index="636" x="415.25" y="367.5"/>
        <he index="637" x="38.25" y="365.5"/>
        <he index="638" x="101.75" y="442.5"/>
        <he index="639" x="285.25" y="607.5"/>
        <he index="640" x="97.25" y="1289.0"/>
        <he index="641" x="335.75" y="752.5"/>
        <he index="642" x="350.75" y="111.0"/>
        <he index="643" x="618.25" y="476.5"/>
        <he index="644" x="59.75" y="208.5"/>
        <he index="645" x="277.75" y="1303.5"/>
        <he index="646" x="291.25" y="408.5"/>
        <he index="647" x="753.75" y="81.0"/>
        <he index="648" x="391.75" y="724.5"/>
        <he index="649" x="764.75" y="155.5"/>
        <he index="650" x="866.25" y="1014.0"/>
        <he index="651" x="684.25" y="954.0"/>
        <he index="652" x="458.75" y="279.0"/>
        <he index="653" x="496.75" y="317.5"/>
        <he index="654" x="697.25" y="780.5"/>
        <he index="655" x="598.75" y="252.0"/>
        <he index="656" x="322.75" y="686.0"/>
        <he index="657" x="238.75" y="627.0"/>
        <he index="658" x="957.25" y="40.5"/>
        <he index="659" x="60.75" y="1411.0"/>
        <he index="660" x="379.75" y="943.0"/>
        <he index="661" x="299.75" y="1340.0"/>
        <he index="662" x="699.75" y="1088.0"/>
        <he index="663" x="306.75" y="482.5"/>
        <he index="664" x="768.25" y="1138.5"/>
        <he index="665" x="802.25" y="801.5"/>
        <he index="666" x="293.25" y="1382.0"/>
        <he index="667" x="601.25" y="1100.0"/>
        <he index="668" x="261.75" y="153.5"/>
        <he index="669" x="292.25" y="224.0"/>
        <he index="670" x="696.75" y="1410.0"/>
        <he index="671" x="89.75" y="1409.5"/>
        <he index="672" x="607.75" y="524.0"/>
        <he index="673" x="145.75" y="832.5"/>
        <he index="674" x="880.75" y="776.5"/>
        <he index="675" x="265.25" y="565.0"/>
        <he index="676" x="957.75" y="607.0"/>
        <he index="677" x="672.25" y="477.0"/>
        <he index="678" x="647.75" y="40.0"/>
        <he index="679" x="927.75" y="600.0"/>
        <he index="680" x="518.75" y="1442.0"/>
        <he index="681" x="422.25" y="603.5"/>
        <he index="682" x="260.75" y="489.0"/>
        <he index="683" x="774.25" y="97.0"/>
        <he index="684" x="93.25" y="1489.5"/>
        <he index="685" x="301.25" y="672.0"/>
        <he index="686" x="413.75" y="528.5"/>
        <he index="687" x="923.25" y="659.0"/>
        <he index="688" x="240.75" y="479.5"/>
        <he index="689" x="259.75" y="922.0"/>
        <he index="690" x="706.25" y="691.0"/>
        <he index="691" x="614.75" y="697.0"/>
        <he index="692" x="641.75" y="551.5"/>
        <he index="693" x="638.75" y="592.5"/>
        <he index="694" x="199.25" y="1156.5"/>
        <he index="695" x="768.25" y="231.5"/>
        <he index="696" x="697.25" y="351.0"/>
        <he index="697" x="249.25" y="415.5"/>
        <he index="698" x="833.75" y="936.5"/>
        <he index="699" x="623.75" y="1087.5"/>
        <he index="700" x="345.25" y="699.5"/>
        <he index="701" x="976.75" y="374.5"/>
        <he index="702" x="560.75" y="181.5"/>
        <he index="703" x="582.75" y="1019.0"/>
        <he index="704" x="288.75" y="581.5"/>
        <he index="705" x="162.25" y="401.0"/>
        <he index="706" x="641.75" y="404.5"/>
        <he index="707" x="279.25" y="947.0"/>
        <he index="708" x="218.75" y="348.5"/>
        <he index="709" x="787.25" y="1026.5"/>
        <he index="710" x="421.75" y="412.0"/>
        <he index="711" x="253.75" y="1044.5"/>
        <he index="712" x="789.75" y="303.0"/>
        <he index="713" x="89.75" y="475.0"/>
        <he index="714" x="462.25" y="772.0"/>
        <he index="715" x="45.75" y="756.5"/>
        <he index="716" x="364.25" y="739.0"/>
        <he index="717" x="206.75" y="752.0"/>
        <he index="718" x="912.75" y="448.5"/>
        <he index="719" x="965.75" y="735.5"/>
        <he index="720" x="639.25" y="112.0"/>
        <he index="721" x="439.75" y="785.0"/>
        <he index="722" x="79.25" y="1130.5"/>
        <he index="723" x="160.25" y="1243.0"/>
        <he index="724" x="484.75" y="860.5"/>
        <he index="725" x="233.25" y="929.5"/>
        <he index="726" x="548.75" y="1431.0"/>
        <he index="727" x="277.25" y="520.0"/>
        <he index="728" x="496.75" y="483.5"/>
        <he index="729" x="255.75" y="511.5"/>
        <he index="730" x="130.75" y="1366.5"/>
        <he index="731" x="868.25" y="67.5"/>
        <he index="732" x="389.75" y="750.5"/>
        <he index="733" x="38.25" y="387.5"/>
        <he index="734" x="247.25" y="785.5"/>
        <he index="735" x="591.75" y="573.5"/>
        <he index="736" x="489.75" y="388.0"/>
        <he index="737" x="1014.75" y="63.5"/>
        <he index="738" x="107.25" y="863.5"/>
        <he index="739" x="45.75" y="1015.0"/>
        <he index="740" x="525.25" y="663.0"/>
        <he index="741" x="664.75" y="967.5"/>
        <he index="742" x="203.25" y="685.0"/>
        <he index="743" x="499.25" y="46.0"/>
        <he index="744" x="369.25" y="712.0"/>
        <he index="745" x="214.25" y="147.5"/>
        <he index="746" x="715.25" y="176.0"/>
        <he index="747" x="505.75" y="180.5"/>
        <he index="748" x="331.75" y="1053.5"/>
        <he index="749" x="142.25" y="386.0"/>
        <he index="750" x="235.25" y="37.5"/>
        <he index="751" x="411.25" y="345.5"/>
        <he index="752" x="603.75" y="160.0"/>
        <he index="753" x="928.25" y="41.5"/>
        <he index="754" x="801.75" y="21.0"/>
        <he index="755" x="399.75" y="1438.5"/>
        <he index="756" x="272.25" y="336.5"/>
        <he index="757" x="64.25" y="1570.5"/>
        <he index="758" x="431.75" y="22.5"/>
        <he index="759" x="488.25" y="461.0"/>
        <he index="760" x="565.75" y="472.5"/>
        <he index="761" x="603.75" y="383.0"/>
        <he index="762" x="777.75" y="332.5"/>
        <he index="763" x="706.75" y="276.0"/>
        <he index="764" x="817.75" y="100.0"/>
        <he index="765" x="802.75" y="1163.0"/>
        <he index="766" x="607.75" y="957.5"/>
        <he index="767" x="502.75" y="508.5"/>
        <he index="768" x="918.75" y="793.5"/>
        <he index="769" x="508.25" y="1146.0"/>
        <he index="770" x="59.25" y="733.5"/>
        <he index="771" x="595.25" y="1237.5"/>
        <he index="772" x="502.25" y="341.0"/>
        <he index="773" x="425.25" y="159.5"/>
        <he index="774" x="512.25" y="292.0"/>
        <he index="775" x="988.25" y="494.0"/>
        <he index="776" x="116.75" y="157.0"/>
        <he index="777" x="617.75" y="360.0"/>
        <he index="778" x="819.25" y="210.5"/>
        <he index="779" x="835.75" y="629.5"/>
        <he index="780" x="950.75" y="122.0"/>
        <he index="781" x="718.75" y="760.5"/>
        <he index="782" x="31.25" y="1252.5"/>
        <he index="783" x="817.75" y="653.0"/>
        <he index="784" x="297.75" y="849.0"/>
        <he index="785" x="724.25" y="345.5"/>
        <he index="786" x="447.25" y="77.5"/>
        <he index="787" x="162.75" y="1563.5"/>
        <he index="788" x="322.75" y="320.5"/>
        <he index="789" x="708.25" y="203.0"/>
        <he index="790" x="270.25" y="423.0"/>
        <he index="791" x="170.25" y="972.5"/>
        <he index="792" x="800.75" y="272.5"/>
        <he index="793" x="854.25" y="168.0"/>
        <he index="794" x="42.25" y="669.0"/>
        <he index="795" x="794.75" y="767.5"/>
        <he index="796" x="483.75" y="1496.0"/>
        <he index="797" x="208.75" y="819.0"/>
        <he index="798" x="736.75" y="317.5"/>
        <he index="799" x="372.75" y="558.0"/>
        <he index="800" x="119.75" y="255.0"/>
        <he index="801" x="71.75" y="955.0"/>
        <he index="802" x="311.25" y="416.0"/>
        <he index="803" x="779.25" y="38.0"/>
        <he index="804" x="686.25" y="710.5"/>
        <he index="805" x="147.75" y="36.0"/>
        <he index="806" x="776.25" y="202.5"/>
        <he index="807" x="44.25" y="712.5"/>
        <he index="808" x="144.25" y="607.0"/>
        <he index="809" x="86.25" y="1330.0"/>
        <he index="810" x="80.25" y="425.0"/>
        <he index="811" x="799.25" y="675.5"/>
        <he index="812" x="239.25" y="386.5"/>
        <he index="813" x="155.75" y="476.5"/>
        <he index="814" x="554.25" y="989.0"/>
        <he index="815" x="110.75" y="922.0"/>
        <he index="816" x="80.75" y="447.0"/>
        <he index="817" x="227.75" y="1555.5"/>
        <he index="818" x="826.75" y="425.0"/>
        <he index="819" x="393.75" y="809.0"/>
        <he index="820" x="791.75" y="1122.0"/>
        <he index="821" x="475.25" y="1073.0"/>
        <he index="822" x="118.25" y="559.0"/>
        <he index="823" x="614.75" y="1183.0"/>
        <he index="824" x="348.75" y="673.5"/>
        <he index="825" x="680.25" y="425.5"/>
        <he index="826" x="234.75" y="311.0"/>
        <he index="827" x="275.25" y="683.0"/>
        <he index="828" x="250.25" y="70.5"/>
        <he index="829" x="196.75" y="285.5"/>
        <he index="830" x="955.75" y="682.0"/>
        <he index="831" x="833.75" y="1286.5"/>
        <he index="832" x="524.25" y="1094.5"/>
        <he index="833" x="710.75" y="1128.0"/>
        <he index="834" x="141.75" y="1124.5"/>
        <he index="835" x="237.25" y="1230.5"/>
        <he index="836" x="388.25" y="135.5"/>
        <he index="837" x="305.75" y="939.0"/>
        <he index="838" x="84.25" y="924.5"/>
        <he index="839" x="512.75" y="398.5"/>
        <he index="840" x="479.75" y="342.5"/>
        <he index="841" x="393.75" y="544.0"/>
        <he index="842" x="611.25" y="128.5"/>
        <he index="843" x="675.75" y="1008.0"/>
        <he index="844" x="423.75" y="86.0"/>
        <he index="845" x="393.25" y="366.0"/>
        <he index="846" x="432.25" y="139.5"/>
        <he index="847" x="497.25" y="1063.0"/>
        <he index="848" x="102.75" y="1011.0"/>
        <he index="849" x="444.75" y="587.5"/>
        <he index="850" x="953.75" y="95.0"/>
        <he index="851" x="649.25" y="783.0"/>
        <he index="852" x="296.75" y="698.0"/>
        <he index="853" x="779.75" y="823.5"/>
        <he index="854" x="594.75" y="190.5"/>
        <he index="855" x="59.25" y="253.0"/>
        <he index="856" x="741.75" y="910.0"/>
        <he index="857" x="322.25" y="840.0"/>
        <he index="858" x="225.25" y="79.0"/>
        <he index="859" x="547.75" y="1345.5"/>
        <he index="860" x="249.25" y="693.0"/>
        <he index="861" x="587.25" y="546.5"/>
        <he index="862" x="375.75" y="407.5"/>
        <he index="863" x="89.25" y="564.0"/>
        <he index="864" x="185.75" y="667.0"/>
        <he index="865" x="31.25" y="1172.5"/>
        <he index="866" x="194.25" y="556.0"/>
        <he index="867" x="513.25" y="558.5"/>
        <he index="868" x="229.75" y="1272.5"/>
        <he index="869" x="59.75" y="450.0"/>
        <he index="870" x="620.25" y="575.5"/>
        <he index="871" x="350.75" y="495.5"/>
        <he index="872" x="361.25" y="1158.5"/>
        <he index="873" x="16.75" y="388.5"/>
        <he index="874" x="730.25" y="94.0"/>
        <he index="875" x="682.75" y="117.0"/>
        <he index="876" x="874.25" y="1210.0"/>
        <he index="877" x="626.75" y="801.0"/>
        <he index="878" x="311.25" y="437.5"/>
        <he index="879" x="243.75" y="1351.0"/>
        <he index="880" x="417.75" y="1022.5"/>
        <he index="881" x="836.25" y="722.5"/>
        <he index="882" x="885.25" y="557.5"/>
        <he index="883" x="311.75" y="906.0"/>
        <he index="884" x="578.75" y="340.0"/>
        <he index="885" x="430.75" y="222.0"/>
        <he index="886" x="281.75" y="497.5"/>
        <he index="887" x="91.75" y="1209.5"/>
        <he index="888" x="279.75" y="824.0"/>
        <he index="889" x="1084.75" y="545.0"/>
        <he index="890" x="722.75" y="925.0"/>
        <he index="891" x="195.25" y="1560.0"/>
        <he index="892" x="629.25" y="291.0"/>
        <he index="893" x="101.25" y="353.5"/>
        <he index="894" x="565.25" y="1207.5"/>
        <he index="895" x="399.75" y="94.5"/>
        <he index="896" x="505.25" y="709.5"/>
        <he index="897" x="311.75" y="393.5"/>
        <he index="898" x="331.75" y="399.5"/>
        <he index="899" x="387.25" y="40.0"/>
        <he index="900" x="175.25" y="1160.0"/>
        <he index="901" x="457.75" y="908.0"/>
        <he index="902" x="607.75" y="229.5"/>
        <he index="903" x="222.75" y="702.0"/>
        <he index="904" x="144.75" y="1525.5"/>
        <he index="905" x="343.25" y="863.5"/>
        <he index="906" x="172.25" y="883.0"/>
        <he index="907" x="969.25" y="662.0"/>
        <he index="908" x="148.25" y="127.5"/>
        <he index="909" x="287.75" y="1220.0"/>
        <he index="910" x="353.75" y="471.5"/>
        <he index="911" x="478.25" y="963.0"/>
        <he index="912" x="136.25" y="169.0"/>
        <he index="913" x="867.75" y="848.5"/>
        <he index="914" x="996.25" y="319.5"/>
        <he index="915" x="733.75" y="1113.5"/>
        <he index="916" x="518.25" y="34.5"/>
        <he index="917" x="590.25" y="1195.5"/>
        <he index="918" x="843.25" y="514.5"/>
        <he index="919" x="304.25" y="646.5"/>
        <he index="920" x="306.75" y="764.5"/>
        <he index="921" x="497.25" y="629.5"/>
        <he index="922" x="784.75" y="551.0"/>
        <he index="923" x="326.25" y="963.0"/>
        <he index="924" x="79.25" y="155.0"/>
        <he index="925" x="662.25" y="526.5"/>
        <he index="926" x="722.25" y="1073.5"/>
        <he index="927" x="734.75" y="419.5"/>
        <he index="928" x="607.25" y="887.5"/>
        <he index="929" x="797.75" y="417.0"/>
        <he index="930" x="57.75" y="926.5"/>
        <he index="931" x="137.75" y="1446.0"/>
        <he index="932" x="248.25" y="865.0"/>
        <he index="933" x="446.25" y="1010.5"/>
        <he index="934" x="552.25" y="747.5"/>
        <he index="935" x="561.75" y="1030.5"/>
        <he index="936" x="277.25" y="775.5"/>
        <he index="937" x="316.75" y="1130.0"/>
        <he index="938" x="62.25" y="1491.0"/>
        <he index="939" x="406.25" y="932.0"/>
        <he index="940" x="840.25" y="322.5"/>
        <he index="941" x="762.75" y="312.0"/>
        <he index="942" x="710.25" y="373.0"/>
        <he index="943" x="828.75" y="482.0"/>
        <he index="944" x="947.25" y="370.0"/>
        <he index="945" x="38.25" y="191.5"/>
        <he index="946" x="657.75" y="218.0"/>
        <he index="947" x="548.75" y="260.0"/>
        <he index="948" x="588.75" y="681.0"/>
        <he index="949" x="604.75" y="50.5"/>
        <he index="950" x="354.25" y="449.0"/>
        <he index="951" x="213.25" y="568.0"/>
        <he index="952" x="794.25" y="112.5"/>
        <he index="953" x="801.75" y="1065.5"/>
        <he index="954" x="464.75" y="390.5"/>
        <he index="955" x="584.25" y="221.0"/>
        <he index="956" x="518.25" y="1314.5"/>
        <he index="957" x="464.75" y="453.5"/>
        <he index="958" x="74.25" y="754.0"/>
        <he index="959" x="869.25" y="958.0"/>
        <he index="960" x="329.75" y="584.5"/>
        <he index="961" x="1014.25" y="438.5"/>
        <he index="962" x="461.75" y="366.5"/>
        <he index="963" x="580.25" y="522.0"/>
        <he index="964" x="1022.75" y="653.5"/>
        <he index="965" x="142.25" y="408.5"/>
        <he index="966" x="481.25" y="275.5"/>
        <he index="967" x="687.25" y="1142.5"/>
        <he index="968" x="108.75" y="1248.0"/>
        <he index="969" x="106.75" y="1069.5"/>
        <he index="970" x="757.75" y="23.5"/>
        <he index="971" x="176.75" y="1031.0"/>
        <he index="972" x="750.25" y="341.0"/>
        <he index="973" x="612.25" y="1048.0"/>
        <he index="974" x="159.75" y="1004.0"/>
        <he index="975" x="374.25" y="385.5"/>
        <he index="976" x="62.75" y="820.5"/>
        <he index="977" x="354.75" y="426.0"/>
        <he index="978" x="488.75" y="1410.5"/>
        <he index="979" x="392.25" y="842.5"/>
        <he index="980" x="227.75" y="427.5"/>
        <he index="981" x="615.75" y="405.0"/>
        <he index="982" x="114.75" y="980.5"/>
        <he index="983" x="540.25" y="1219.0"/>
        <he index="984" x="604.75" y="1365.0"/>
        <he index="985" x="955.75" y="67.5"/>
        <he index="986" x="850.75" y="1128.5"/>
        <he index="987" x="79.75" y="247.5"/>
        <he index="988" x="410.25" y="898.5"/>
        <he index="989" x="539.25" y="564.5"/>
        <he index="990" x="31.25" y="869.5"/>
        <he index="991" x="583.25" y="450.5"/>
        <he index="992" x="411.75" y="1184.0"/>
        <he index="993" x="796.75" y="1262.5"/>
        <he index="994" x="770.25" y="1279.0"/>
        <he index="995" x="694.75" y="1366.0"/>
        <he index="996" x="325.25" y="119.5"/>
        <he index="997" x="726.25" y="121.5"/>
        <he index="998" x="92.25" y="664.0"/>
        <he index="999" x="38.25" y="344.0"/>
        <he index="1000" x="120.75" y="301.5"/>
        <he index="1001" x="843.75" y="51.0"/>
        <he index="1002" x="188.25" y="52.0"/>
        <he index="1003" x="242.25" y="556.5"/>
        <he index="1004" x="705.25" y="850.5"/>
        <he index="1005" x="229.25" y="523.5"/>
        <he index="1006" x="352.25" y="622.0"/>
        <he index="1007" x="235.25" y="651.5"/>
        <he index="1008" x="80.25" y="359.0"/>
        <he index="1009" x="365.75" y="1488.0"/>
        <he index="1010" x="328.25" y="248.0"/>
        <he index="1011" x="38.75" y="169.5"/>
        <he index="1012" x="605.75" y="853.5"/>
        <he index="1013" x="696.75" y="159.5"/>
        <he index="1014" x="615.75" y="206.5"/>
        <he index="1015" x="59.75" y="406.5"/>
        <he index="1016" x="1008.25" y="601.5"/>
        <he index="1017" x="656.75" y="380.0"/>
        <he index="1018" x="654.75" y="287.5"/>
        <he index="1019" x="79.75" y="225.0"/>
        <he index="1020" x="237.25" y="17.0"/>
        <he index="1021" x="141.75" y="363.0"/>
        <he index="1022" x="575.75" y="1334.0"/>
        <he index="1023" x="838.25" y="401.0"/>
        <he index="1024" x="344.25" y="36.0"/>
        <he index="1025" x="197.75" y="1439.0"/>
        <he index="1026" x="653.25" y="502.5"/>
        <he index="1027" x="241.75" y="897.0"/>
        <he index="1028" x="346.25" y="987.0"/>
        <he index="1029" x="1020.25" y="580.5"/>
        <he index="1030" x="1073.25" y="567.0"/>
        <he index="1031" x="478.25" y="502.0"/>
        <he index="1032" x="303.75" y="505.0"/>
        <he index="1033" x="677.25" y="1102.0"/>
        <he index="1034" x="231.25" y="839.0"/>
        <he index="1035" x="161.25" y="354.5"/>
        <he index="1036" x="385.25" y="1151.0"/>
        <he index="1037" x="451.25" y="976.0"/>
        <he index="1038" x="793.25" y="223.0"/>
        <he index="1039" x="733.25" y="194.0"/>
        <he index="1040" x="668.75" y="54.0"/>
        <he index="1041" x="358.75" y="920.0"/>
        <he index="1042" x="222.75" y="871.5"/>
        <he index="1043" x="288.25" y="453.0"/>
        <he index="1044" x="59.25" y="275.0"/>
        <he index="1045" x="698.25" y="657.0"/>
        <he index="1046" x="663.25" y="451.5"/>
        <he index="1047" x="671.75" y="554.0"/>
        <he index="1048" x="813.75" y="846.0"/>
        <he index="1049" x="703.25" y="1225.5"/>
        <he index="1050" x="307.25" y="621.0"/>
        <he index="1051" x="406.25" y="264.0"/>
        <he index="1052" x="358.75" y="242.5"/>
        <he index="1053" x="718.25" y="447.5"/>
        <he index="1054" x="843.25" y="217.5"/>
        <he index="1055" x="708.25" y="602.0"/>
        <he index="1056" x="581.75" y="93.5"/>
        <he index="1057" x="252.25" y="954.5"/>
        <he index="1058" x="388.75" y="18.5"/>
        <he index="1059" x="351.75" y="382.5"/>
        <he index="1060" x="90.25" y="774.5"/>
        <he index="1061" x="779.75" y="606.5"/>
        <he index="1062" x="221.25" y="610.0"/>
        <he index="1063" x="665.75" y="729.5"/>
        <he index="1064" x="689.75" y="451.0"/>
        <he index="1065" x="429.75" y="487.0"/>
        <he index="1066" x="80.25" y="337.0"/>
        <he index="1067" x="779.25" y="1082.0"/>
        <he index="1068" x="490.75" y="1325.0"/>
        <he index="1069" x="134.75" y="679.0"/>
        <he index="1070" x="162.75" y="424.0"/>
        <he index="1071" x="579.25" y="800.0"/>
        <he index="1072" x="303.75" y="815.5"/>
        <he index="1073" x="812.25" y="314.0"/>
        <he index="1074" x="418.25" y="735.5"/>
        <he index="1075" x="70.25" y="1291.0"/>
        <he index="1076" x="169.25" y="716.5"/>
        <he index="1077" x="848.75" y="1228.0"/>
        <he index="1078" x="936.75" y="396.5"/>
        <he index="1079" x="669.75" y="307.5"/>
        <he index="1080" x="219.75" y="373.0"/>
        <he index="1081" x="195.25" y="260.0"/>
        <he index="1082" x="459.25" y="1420.5"/>
        <he index="1083" x="236.75" y="336.5"/>
        <he index="1084" x="97.75" y="707.5"/>
        <he index="1085" x="497.75" y="657.0"/>
        <he index="1086" x="916.25" y="282.0"/>
        <he index="1087" x="57.25" y="1251.5"/>
        <he index="1088" x="466.75" y="570.0"/>
        <he index="1089" x="488.75" y="1452.5"/>
        <he index="1090" x="427.25" y="1471.5"/>
        <he index="1091" x="59.25" y="384.5"/>
        <he index="1092" x="692.25" y="745.5"/>
        <he index="1093" x="899.75" y="474.0"/>
        <he index="1094" x="310.25" y="570.5"/>
        <he index="1095" x="672.25" y="641.5"/>
        <he index="1096" x="576.25" y="766.0"/>
        <he index="1097" x="108.25" y="794.0"/>
        <he index="1098" x="119.75" y="770.5"/>
        <he index="1099" x="206.75" y="845.5"/>
        <he index="1100" x="473.25" y="321.5"/>
        <he index="1101" x="69.25" y="896.5"/>
        <he index="1102" x="723.25" y="1351.5"/>
        <he index="1103" x="102.25" y="1369.0"/>
        <he index="1104" x="633.75" y="940.5"/>
        <he index="1105" x="461.75" y="840.0"/>
        <he index="1106" x="203.25" y="458.5"/>
        <he index="1107" x="174.75" y="544.0"/>
        <he index="1108" x="937.25" y="312.0"/>
        <he index="1109" x="972.25" y="460.5"/>
        <he index="1110" x="878.75" y="302.5"/>
        <he index="1111" x="99.75" y="240.0"/>
        <he index="1112" x="894.75" y="251.5"/>
        <he index="1113" x="400.25" y="479.5"/>
        <he index="1114" x="769.75" y="126.5"/>
        <he index="1115" x="113.75" y="837.5"/>
        <he index="1116" x="928.25" y="338.5"/>
        <he index="1117" x="183.25" y="1089.0"/>
        <he index="1118" x="407.25" y="52.5"/>
        <he index="1119" x="1045.25" y="32.0"/>
        <he index="1120" x="195.25" y="1057.0"/>
        <he index="1121" x="396.25" y="697.5"/>
        <he index="1122" x="633.75" y="527.0"/>
        <he index="1123" x="662.75" y="104.0"/>
        <he index="1124" x="509.25" y="362.0"/>
        <he index="1125" x="652.75" y="428.0"/>
        <he index="1126" x="958.75" y="487.5"/>
        <he index="1127" x="716.75" y="249.0"/>
        <he index="1128" x="519.25" y="1053.0"/>
        <he index="1129" x="640.25" y="202.0"/>
        <he index="1130" x="60.25" y="1044.0"/>
        <he index="1131" x="531.75" y="74.5"/>
        <he index="1132" x="602.75" y="628.5"/>
        <he index="1133" x="630.75" y="1309.0"/>
        <he index="1134" x="663.25" y="608.5"/>
        <he index="1135" x="630.25" y="381.5"/>
        <he index="1136" x="691.75" y="39.0"/>
        <he index="1137" x="452.75" y="35.0"/>
        <he index="1138" x="298.75" y="972.0"/>
        <he index="1139" x="370.25" y="820.5"/>
        <he index="1140" x="38.25" y="409.0"/>
        <he index="1141" x="737.25" y="1252.0"/>
        <he index="1142" x="556.25" y="816.5"/>
        <he index="1143" x="421.75" y="304.0"/>
        <he index="1144" x="702.25" y="133.0"/>
        <he index="1145" x="689.75" y="1047.0"/>
        <he index="1146" x="388.25" y="876.0"/>
        <he index="1147" x="302.25" y="1062.0"/>
        <he index="1148" x="136.75" y="573.0"/>
        <he index="1149" x="351.25" y="647.5"/>
        <he index="1150" x="498.75" y="1018.0"/>
        <he index="1151" x="488.25" y="552.0"/>
        <he index="1152" x="637.25" y="1437.5"/>
        <he index="1153" x="44.25" y="956.5"/>
        <he index="1154" x="695.75" y="302.5"/>
        <he index="1155" x="546.25" y="617.0"/>
        <he index="1156" x="262.25" y="1225.5"/>
        <he index="1157" x="337.75" y="1207.0"/>
        <he index="1158" x="437.25" y="1259.5"/>
        <he index="1159" x="224.75" y="1051.5"/>
        <he index="1160" x="367.75" y="342.0"/>
        <he index="1161" x="370.75" y="364.0"/>
        <he index="1162" x="231.25" y="58.5"/>
        <he index="1163" x="136.25" y="1066.0"/>
        <he index="1164" x="563.75" y="403.5"/>
        <he index="1165" x="620.75" y="1225.0"/>
        <he index="1166" x="100.75" y="286.0"/>
        <he index="1167" x="460.25" y="1166.0"/>
        <he index="1168" x="331.25" y="558.5"/>
        <he index="1169" x="223.75" y="1314.0"/>
        <he index="1170" x="874.75" y="675.0"/>
        <he index="1171" x="181.75" y="392.5"/>
        <he index="1172" x="406.75" y="148.0"/>
        <he index="1173" x="137.25" y="918.5"/>
        <he index="1174" x="897.25" y="69.0"/>
        <he index="1175" x="79.75" y="178.5"/>
        <he index="1176" x="535.25" y="1177.5"/>
        <he index="1177" x="268.25" y="183.0"/>
        <he index="1178" x="100.25" y="263.0"/>
        <he index="1179" x="849.25" y="976.0"/>
        <he index="1180" x="254.25" y="667.5"/>
        <he index="1181" x="160.75" y="331.0"/>
        <he index="1182" x="201.75" y="407.0"/>
        <he index="1183" x="282.75" y="1037.5"/>
        <he index="1184" x="873.75" y="1110.5"/>
        <he index="1185" x="893.25" y="650.5"/>
        <he index="1186" x="578.25" y="1112.0"/>
        <he index="1187" x="907.75" y="200.0"/>
        <he index="1188" x="198.25" y="776.5"/>
        <he index="1189" x="351.75" y="571.5"/>
        <he index="1190" x="557.25" y="851.0"/>
        <he index="1191" x="367.75" y="853.0"/>
        <he index="1192" x="942.25" y="176.0"/>
        <he index="1193" x="38.25" y="430.5"/>
        <he index="1194" x="47.75" y="800.0"/>
        <he index="1195" x="588.75" y="274.5"/>
        <he index="1196" x="573.75" y="496.5"/>
        <he index="1197" x="278.25" y="41.0"/>
        <he index="1198" x="573.25" y="427.5"/>
        <he index="1199" x="959.25" y="548.0"/>
        <he index="1200" x="59.25" y="428.5"/>
        <he index="1201" x="369.75" y="1446.5"/>
        <he index="1202" x="823.25" y="1245.5"/>
        <he index="1203" x="733.25" y="705.0"/>
        <he index="1204" x="450.25" y="56.5"/>
        <he index="1205" x="200.25" y="83.5"/>
        <he index="1206" x="58.25" y="533.0"/>
        <he index="1207" x="634.25" y="679.0"/>
        <he index="1208" x="103.25" y="1168.5"/>
        <he index="1209" x="456.25" y="345.0"/>
        <he index="1210" x="17.25" y="172.5"/>
        <he index="1211" x="681.75" y="869.5"/>
        <he index="1212" x="604.25" y="818.5"/>
        <he index="1213" x="543.25" y="308.0"/>
        <he index="1214" x="710.25" y="80.0"/>
        <he index="1215" x="209.75" y="513.0"/>
        <he index="1216" x="331.25" y="377.5"/>
        <he index="1217" x="185.75" y="1239.0"/>
        <he index="1218" x="531.75" y="797.5"/>
        <he index="1219" x="83.25" y="687.0"/>
        <he index="1220" x="485.25" y="826.5"/>
        <he index="1221" x="184.25" y="578.0"/>
        <he index="1222" x="124.25" y="703.0"/>
        <he index="1223" x="800.75" y="472.0"/>
        <he index="1224" x="473.75" y="998.0"/>
        <he index="1225" x="789.25" y="1220.0"/>
        <he index="1226" x="436.75" y="1301.5"/>
        <he index="1227" x="388.75" y="1523.5"/>
        <he index="1228" x="214.25" y="272.5"/>
        <he index="1229" x="554.25" y="518.0"/>
        <he index="1230" x="411.25" y="503.0"/>
        <he index="1231" x="744.25" y="650.0"/>
        <he index="1232" x="845.25" y="18.5"/>
        <he index="1233" x="516.75" y="245.5"/>
        <he index="1234" x="379.25" y="1361.0"/>
        <he index="1235" x="121.75" y="392.5"/>
        <he index="1236" x="55.25" y="646.0"/>
        <he index="1237" x="578.75" y="1419.5"/>
        <he index="1238" x="156.25" y="808.5"/>
        <he index="1239" x="548.25" y="424.5"/>
        <he index="1240" x="725.25" y="670.5"/>
        <he index="1241" x="644.75" y="748.0"/>
        <he index="1242" x="837.75" y="1088.5"/>
        <he index="1243" x="286.75" y="195.0"/>
        <he index="1244" x="758.75" y="484.5"/>
        <he index="1245" x="154.25" y="587.0"/>
        <he index="1246" x="463.25" y="737.5"/>
        <he index="1247" x="800.25" y="51.5"/>
        <he index="1248" x="778.75" y="878.5"/>
        <he index="1249" x="512.25" y="87.0"/>
        <he index="1250" x="500.75" y="20.5"/>
        <he index="1251" x="954.25" y="428.5"/>
        <he index="1252" x="505.25" y="442.0"/>
        <he index="1253" x="852.75" y="606.0"/>
        <he index="1254" x="469.75" y="595.5"/>
        <he index="1255" x="980.25" y="121.5"/>
        <he index="1256" x="829.25" y="266.5"/>
        <he index="1257" x="375.25" y="608.5"/>
        <he index="1258" x="318.75" y="996.5"/>
        <he index="1259" x="463.25" y="1335.0"/>
        <he index="1260" x="739.75" y="740.0"/>
        <he index="1261" x="645.75" y="627.5"/>
        <he index="1262" x="127.25" y="1166.5"/>
        <he index="1263" x="141.25" y="316.5"/>
        <he index="1264" x="864.75" y="640.0"/>
        <he index="1265" x="397.25" y="671.5"/>
        <he index="1266" x="668.25" y="1061.0"/>
        <he index="1267" x="1064.75" y="495.0"/>
        <he index="1268" x="572.75" y="1292.0"/>
        <he index="1269" x="318.25" y="712.0"/>
        <he index="1270" x="215.75" y="903.5"/>
        <he index="1271" x="460.25" y="874.0"/>
        <he index="1272" x="384.25" y="61.0"/>
        <he index="1273" x="576.75" y="1463.0"/>
        <he index="1274" x="531.75" y="901.0"/>
        <he index="1275" x="540.75" y="1042.0"/>
        <he index="1276" x="756.75" y="844.5"/>
        <he index="1277" x="98.75" y="952.5"/>
        <he index="1278" x="315.75" y="189.0"/>
        <he index="1279" x="427.75" y="65.0"/>
        <he index="1280" x="756.75" y="949.0"/>
        <he index="1281" x="547.25" y="1389.0"/>
        <he index="1282" x="17.25" y="713.5"/>
        <he index="1283" x="849.75" y="377.0"/>
        <he index="1284" x="509.25" y="846.5"/>
        <he index="1285" x="607.25" y="1142.0"/>
        <he index="1286" x="317.25" y="1417.5"/>
        <he index="1287" x="655.75" y="852.5"/>
        <he index="1288" x="215.75" y="20.5"/>
        <he index="1289" x="369.25" y="123.5"/>
        <he index="1290" x="147.75" y="1035.5"/>
        <he index="1291" x="517.25" y="1272.0"/>
        <he index="1292" x="387.25" y="1192.0"/>
        <he index="1293" x="318.25" y="873.0"/>
        <he index="1294" x="237.75" y="361.5"/>
        <he index="1295" x="1018.75" y="498.0"/>
        <he index="1296" x="190.75" y="501.5"/>
        <he index="1297" x="96.75" y="1569.0"/>
        <he index="1298" x="138.75" y="245.5"/>
        <he index="1299" x="898.75" y="590.5"/>
        <he index="1300" x="17.25" y="757.5"/>
        <he index="1301" x="17.25" y="899.0"/>
        <he index="1302" x="607.25" y="923.0"/>
        <he index="1303" x="1006.75" y="378.0"/>
        <he index="1304" x="129.75" y="1566.5"/>
        <he index="1305" x="1004.75" y="526.0"/>
        <he index="1306" x="863.75" y="1168.5"/>
        <he index="1307" x="419.25" y="709.5"/>
        <he index="1308" x="435.25" y="886.5"/>
        <he index="1309" x="17.25" y="957.5"/>
        <he index="1310" x="494.75" y="251.0"/>
        <he index="1311" x="59.25" y="985.0"/>
        <he index="1312" x="832.25" y="884.0"/>
        <he index="1313" x="706.75" y="424.5"/>
        <he index="1314" x="1032.25" y="559.5"/>
        <he index="1315" x="17.25" y="1133.0"/>
        <he index="1316" x="148.75" y="765.5"/>
        <he index="1317" x="256.25" y="1267.5"/>
        <he index="1318" x="670.75" y="764.5"/>
        <he index="1319" x="824.25" y="779.0"/>
        <he index="1320" x="837.75" y="115.5"/>
        <he index="1321" x="519.75" y="1356.5"/>
        <he index="1322" x="17.25" y="259.0"/>
        <he index="1323" x="839.25" y="1186.5"/>
        <he index="1324" x="445.75" y="718.5"/>
        <he index="1325" x="264.75" y="467.0"/>
        <he index="1326" x="366.75" y="27.5"/>
        <he index="1327" x="159.25" y="1363.5"/>
        <he index="1328" x="269.75" y="1142.0"/>
        <he index="1329" x="774.25" y="986.5"/>
        <he index="1330" x="101.25" y="420.5"/>
        <he index="1331" x="17.25" y="670.0"/>
        <he index="1332" x="270.25" y="543.5"/>
        <he index="1333" x="702.25" y="814.5"/>
        <he index="1334" x="1001.75" y="466.5"/>
        <he index="1335" x="623.25" y="33.0"/>
        <he index="1336" x="239.75" y="810.5"/>
        <he index="1337" x="921.25" y="121.0"/>
        <he index="1338" x="240.25" y="1513.5"/>
        <he index="1339" x="841.25" y="83.5"/>
        <he index="1340" x="634.75" y="136.0"/>
        <he index="1341" x="346.25" y="1411.0"/>
        <he index="1342" x="886.25" y="499.0"/>
        <he index="1343" x="59.25" y="231.0"/>
        <he index="1344" x="225.25" y="961.5"/>
        <he index="1345" x="823.75" y="1049.0"/>
        <he index="1346" x="215.75" y="993.5"/>
        <he index="1347" x="198.25" y="310.5"/>
        <he index="1348" x="744.25" y="1154.0"/>
        <he index="1349" x="814.75" y="1105.5"/>
        <he index="1350" x="436.25" y="282.0"/>
        <he index="1351" x="869.25" y="582.0"/>
        <he index="1352" x="56.75" y="868.0"/>
        <he index="1353" x="581.25" y="973.5"/>
        <he index="1354" x="569.25" y="1249.5"/>
        <he index="1355" x="162.25" y="378.0"/>
        <he index="1356" x="416.25" y="831.0"/>
        <he index="1357" x="486.25" y="1198.5"/>
        <he index="1358" x="413.25" y="127.5"/>
        <he index="1359" x="219.75" y="176.5"/>
        <he index="1360" x="865.75" y="93.0"/>
        <he index="1361" x="550.25" y="642.5"/>
        <he index="1362" x="608.25" y="1407.0"/>
        <he index="1363" x="546.75" y="1083.5"/>
        <he index="1364" x="80.75" y="201.5"/>
        <he index="1365" x="470.75" y="479.0"/>
        <he index="1366" x="389.25" y="1033.5"/>
        <he index="1367" x="930.75" y="229.5"/>
        <he index="1368" x="227.75" y="1434.5"/>
        <he index="1369" x="293.75" y="551.0"/>
        <he index="1370" x="752.75" y="684.5"/>
        <he index="1371" x="750.25" y="109.5"/>
        <he index="1372" x="163.75" y="914.0"/>
        <he index="1373" x="207.75" y="63.0"/>
        <he index="1374" x="557.25" y="885.5"/>
        <he index="1375" x="399.75" y="457.0"/>
        <he index="1376" x="437.75" y="852.5"/>
        <he index="1377" x="17.25" y="1016.0"/>
        <he index="1378" x="404.25" y="73.5"/>
        <he index="1379" x="290.75" y="1005.0"/>
        <he index="1380" x="871.25" y="901.5"/>
        <he index="1381" x="689.75" y="65.0"/>
        <he index="1382" x="152.75" y="1093.5"/>
        <he index="1383" x="603.75" y="1006.5"/>
        <he index="1384" x="869.75" y="42.5"/>
        <he index="1385" x="758.75" y="261.0"/>
        <he index="1386" x="202.25" y="534.5"/>
        <he index="1387" x="985.25" y="66.0"/>
        <he index="1388" x="842.25" y="458.0"/>
        <he index="1389" x="242.75" y="718.5"/>
        <he index="1390" x="272.75" y="857.5"/>
        <he index="1391" x="755.25" y="1379.5"/>
        <he index="1392" x="118.75" y="182.0"/>
        <he index="1393" x="137.25" y="464.0"/>
        <he index="1394" x="995.25" y="695.0"/>
        <he index="1395" x="31.25" y="1412.0"/>
        <he index="1396" x="112.75" y="1528.0"/>
        <he index="1397" x="334.75" y="1495.5"/>
        <he index="1398" x="350.75" y="796.5"/>
        <he index="1399" x="824.75" y="595.5"/>
        <he index="1400" x="668.25" y="403.0"/>
        <he index="1401" x="177.75" y="759.0"/>
        <he index="1402" x="815.75" y="745.0"/>
        <he index="1403" x="508.25" y="881.0"/>
        <he index="1404" x="211.25" y="1235.0"/>
        <he index="1405" x="443.25" y="98.5"/>
        <he index="1406" x="473.25" y="701.0"/>
        <he index="1407" x="784.25" y="253.0"/>
        <he index="1408" x="16.75" y="801.0"/>
        <he index="1409" x="877.75" y="198.0"/>
        <he index="1410" x="17.25" y="237.5"/>
        <he index="1411" x="176.75" y="1281.0"/>
        <he index="1412" x="501.25" y="1105.0"/>
        <he index="1413" x="293.75" y="74.5"/>
        <he index="1414" x="59.25" y="163.5"/>
        <he index="1415" x="489.25" y="1240.0"/>
        <he index="1416" x="324.75" y="1086.0"/>
        <he index="1417" x="633.25" y="1352.0"/>
        <he index="1418" x="380.75" y="82.0"/>
        <he index="1419" x="539.25" y="469.5"/>
        <he index="1420" x="683.25" y="377.5"/>
        <he index="1421" x="699.75" y="230.0"/>
        <he index="1422" x="832.75" y="147.0"/>
        <he index="1423" x="138.75" y="789.5"/>
        <he index="1424" x="141.75" y="722.0"/>
        <he index="1425" x="293.25" y="1136.5"/>
        <he index="1426" x="895.75" y="416.0"/>
        <he index="1427" x="413.25" y="1056.0"/>
        <he index="1428" x="420.25" y="578.5"/>
        <he index="1429" x="196.75" y="480.5"/>
        <he index="1430" x="364.25" y="49.0"/>
        <he index="1431" x="77.75" y="1450.0"/>
        <he index="1432" x="141.75" y="655.5"/>
        <he index="1433" x="309.25" y="1460.5"/>
        <he index="1434" x="545.75" y="1474.5"/>
        <he index="1435" x="82.75" y="1250.0"/>
        <he index="1436" x="659.75" y="922.5"/>
        <he index="1437" x="166.25" y="1062.0"/>
        <he index="1438" x="323.75" y="23.5"/>
        <he index="1439" x="785.25" y="440.0"/>
        <he index="1440" x="250.25" y="533.5"/>
        <he index="1441" x="49.25" y="1531.5"/>
        <he index="1442" x="419.25" y="763.0"/>
        <he index="1443" x="601.75" y="783.5"/>
        <he index="1444" x="187.75" y="180.5"/>
        <he index="1445" x="452.25" y="496.0"/>
        <he index="1446" x="312.75" y="87.0"/>
        <he index="1447" x="677.75" y="1240.0"/>
        <he index="1448" x="159.25" y="283.0"/>
        <he index="1449" x="758.25" y="184.5"/>
        <he index="1450" x="217.25" y="323.5"/>
        <he index="1451" x="210.75" y="660.0"/>
        <he index="1452" x="658.75" y="128.5"/>
        <he index="1453" x="569.25" y="596.0"/>
        <he index="1454" x="17.25" y="1074.5"/>
        <he index="1455" x="377.25" y="453.0"/>
        <he index="1456" x="246.25" y="1147.5"/>
        <he index="1457" x="657.25" y="333.0"/>
        <he index="1458" x="16.75" y="302.5"/>
        <he index="1459" x="38.25" y="322.0"/>
        <he index="1460" x="514.75" y="464.5"/>
        <he index="1461" x="243.75" y="987.0"/>
        <he index="1462" x="57.25" y="141.0"/>
        <he index="1463" x="118.75" y="1039.0"/>
        <he index="1464" x="428.25" y="954.5"/>
        <he index="1465" x="703.25" y="514.0"/>
        <he index="1466" x="666.25" y="79.0"/>
        <he index="1467" x="716.25" y="1310.0"/>
        <he index="1468" x="215.25" y="727.0"/>
        <he index="1469" x="16.75" y="1532.0"/>
        <he index="1470" x="857.75" y="490.5"/>
        <he index="1471" x="462.75" y="545.0"/>
        <he index="1472" x="794.75" y="917.5"/>
        <he index="1473" x="732.75" y="1017.5"/>
        <he index="1474" x="339.75" y="1453.5"/>
        <he index="1475" x="724.75" y="795.0"/>
        <he index="1476" x="845.25" y="1031.5"/>
        <he index="1477" x="368.25" y="1010.0"/>
        <he index="1478" x="308.25" y="1256.0"/>
        <he index="1479" x="568.75" y="697.5"/>
        <he index="1480" x="287.25" y="1424.0"/>
        <he index="1481" x="43.25" y="898.5"/>
        <he index="1482" x="537.25" y="403.0"/>
        <he index="1483" x="80.25" y="292.5"/>
        <he index="1484" x="328.25" y="635.0"/>
        <he index="1485" x="280.75" y="20.0"/>
        <he index="1486" x="812.25" y="1346.5"/>
        <he index="1487" x="984.75" y="433.0"/>
        <he index="1488" x="292.75" y="1544.5"/>
        <he index="1489" x="986.75" y="38.0"/>
        <he index="1490" x="289.75" y="388.0"/>
        <he index="1491" x="603.25" y="1321.5"/>
        <he index="1492" x="160.25" y="673.5"/>
        <he index="1493" x="583.75" y="1154.5"/>
        <he index="1494" x="454.75" y="942.5"/>
        <he index="1495" x="317.75" y="66.0"/>
        <he index="1496" x="446.25" y="692.5"/>
        <he index="1497" x="828.25" y="538.5"/>
        <he index="1498" x="128.75" y="538.5"/>
        <he index="1499" x="858.75" y="143.0"/>
        <he index="1500" x="398.25" y="593.5"/>
        <he index="1501" x="270.25" y="708.5"/>
        <he index="1502" x="728.75" y="1210.5"/>
        <he index="1503" x="353.75" y="404.0"/>
        <he index="1504" x="422.25" y="436.0"/>
        <he index="1505" x="278.75" y="1466.5"/>
        <he index="1506" x="38.25" y="235.0"/>
        <he index="1507" x="371.75" y="686.0"/>
        <he index="1508" x="557.25" y="920.0"/>
        <he index="1509" x="758.25" y="429.0"/>
        <he index="1510" x="732.25" y="269.5"/>
        <he index="1511" x="514.75" y="1486.0"/>
        <he index="1512" x="639.25" y="1170.0"/>
        <he index="1513" x="131.75" y="746.5"/>
        <he index="1514" x="81.75" y="841.0"/>
        <he index="1515" x="665.75" y="193.0"/>
        <he index="1516" x="279.25" y="657.5"/>
        <he index="1517" x="321.25" y="45.0"/>
        <he index="1518" x="101.25" y="398.5"/>
        <he index="1519" x="756.25" y="52.5"/>
        <he index="1520" x="508.75" y="533.0"/>
        <he index="1521" x="654.25" y="1116.0"/>
        <he index="1522" x="646.25" y="1211.5"/>
        <he index="1523" x="865.75" y="733.0"/>
        <he index="1524" x="774.25" y="283.0"/>
        <he index="1525" x="646.25" y="1074.5"/>
        <he index="1526" x="499.75" y="682.5"/>
        <he index="1527" x="411.25" y="1226.0"/>
        <he index="1528" x="683.75" y="329.0"/>
        <he index="1529" x="112.75" y="613.5"/>
        <he index="1530" x="986.75" y="347.0"/>
        <he index="1531" x="87.25" y="983.0"/>
        <he index="1532" x="280.75" y="115.0"/>
        <he index="1533" x="418.25" y="552.5"/>
        <he index="1534" x="430.75" y="1091.5"/>
        <he index="1535" x="508.75" y="778.0"/>
        <he index="1536" x="441.75" y="1044.0"/>
        <he index="1537" x="398.75" y="645.0"/>
        <he index="1538" x="599.75" y="499.5"/>
        <he index="1539" x="148.25" y="1405.0"/>
        <he index="1540" x="331.75" y="1291.0"/>
        <he index="1541" x="168.75" y="783.5"/>
        <he index="1542" x="248.25" y="436.0"/>
        <he index="1543" x="486.25" y="792.0"/>
        <he index="1544" x="433.25" y="512.5"/>
        <he index="1545" x="887.25" y="277.0"/>
        <he index="1546" x="197.75" y="967.0"/>
        <he index="1547" x="75.75" y="132.5"/>
        <he index="1548" x="530.75" y="763.0"/>
        <he index="1549" x="584.25" y="645.5"/>
        <he index="1550" x="860.25" y="1268.5"/>
        <he index="1551" x="828.75" y="993.0"/>
        <he index="1552" x="871.75" y="524.0"/>
        <he index="1553" x="597.75" y="749.0"/>
        <he index="1554" x="254.75" y="50.0"/>
        <he index="1555" x="267.25" y="283.5"/>
        <he index="1556" x="214.75" y="635.5"/>
        <he index="1557" x="559.75" y="1166.0"/>
        <he index="1558" x="772.25" y="517.0"/>
        <he index="1559" x="424.25" y="988.0"/>
        <he index="1560" x="620.75" y="610.5"/>
        <he index="1561" x="95.75" y="509.5"/>
        <he index="1562" x="771.75" y="663.0"/>
        <he index="1563" x="192.75" y="31.0"/>
        <he index="1564" x="760.25" y="719.0"/>
        <he index="1565" x="228.75" y="677.0"/>
        <he index="1566" x="572.25" y="251.0"/>
        <he index="1567" x="341.25" y="57.5"/>
        <he index="1568" x="332.25" y="444.0"/>
        <he index="1569" x="953.25" y="258.5"/>
        <he index="1570" x="334.25" y="1249.0"/>
        <he index="1571" x="31.25" y="1332.0"/>
        <he index="1572" x="267.75" y="889.5"/>
        <he index="1573" x="885.25" y="831.0"/>
        <he index="1574" x="201.25" y="383.5"/>
        <he index="1575" x="725.25" y="221.5"/>
        <he index="1576" x="59.25" y="363.0"/>
        <he index="1577" x="543.75" y="590.0"/>
        <he index="1578" x="399.25" y="168.0"/>
        <he index="1579" x="17.25" y="194.0"/>
        <he index="1580" x="743.75" y="1294.5"/>
        <he index="1581" x="447.75" y="470.5"/>
        <he index="1582" x="141.75" y="1205.0"/>
        <he index="1583" x="560.25" y="543.5"/>
        <he index="1584" x="356.25" y="90.5"/>
        <he index="1585" x="396.75" y="775.0"/>
        <he index="1586" x="46.75" y="1074.0"/>
        <he index="1587" x="609.25" y="452.0"/>
        <he index="1588" x="482.75" y="527.5"/>
        <he index="1589" x="461.25" y="1208.5"/>
        <he index="1590" x="353.25" y="953.5"/>
        <he index="1591" x="233.75" y="1109.0"/>
        <he index="1592" x="728.75" y="830.5"/>
        <he index="1593" x="807.75" y="162.0"/>
        <he index="1594" x="168.25" y="1442.5"/>
        <he index="1595" x="864.25" y="794.5"/>
        <he index="1596" x="343.75" y="131.0"/>
        <he index="1597" x="725.25" y="581.5"/>
        <he index="1598" x="534.25" y="538.5"/>
        <he index="1599" x="121.25" y="347.5"/>
        <he index="1600" x="151.25" y="16.0"/>
        <he index="1601" x="741.25" y="560.5"/>
        <he index="1602" x="700.25" y="474.5"/>
        <he index="1603" x="118.25" y="207.5"/>
        <he index="1604" x="235.25" y="743.5"/>
        <he index="1605" x="739.75" y="166.0"/>
        <he index="1606" x="929.25" y="481.5"/>
        <he index="1607" x="883.75" y="441.5"/>
        <he index="1608" x="119.25" y="231.5"/>
        <he index="1609" x="651.75" y="1254.0"/>
        <he index="1610" x="536.25" y="20.0"/>
        <he index="1611" x="631.75" y="870.5"/>
        <he index="1612" x="867.75" y="1311.5"/>
        <he index="1613" x="352.25" y="545.5"/>
        <he index="1614" x="846.75" y="663.5"/>
        <he index="1615" x="354.75" y="1326.5"/>
        <he index="1616" x="285.25" y="475.0"/>
        <he index="1617" x="314.25" y="738.0"/>
        <he index="1618" x="382.25" y="1318.5"/>
        <he index="1619" x="489.25" y="296.5"/>
        <he index="1620" x="409.75" y="31.5"/>
        <he index="1621" x="522.25" y="637.5"/>
        <he index="1622" x="126.25" y="949.5"/>
        <he index="1623" x="374.25" y="660.0"/>
        <he index="1624" x="617.75" y="314.5"/>
        <he index="1625" x="649.25" y="243.0"/>
        <he index="1626" x="768.75" y="573.0"/>
        <he index="1627" x="744.25" y="1058.0"/>
        <he index="1628" x="613.25" y="272.5"/>
        <he index="1629" x="17.25" y="844.5"/>
        <he index="1630" x="78.25" y="797.5"/>
        <he index="1631" x="899.75" y="17.0"/>
        <he index="1632" x="814.25" y="953.5"/>
        <he index="1633" x="17.25" y="216.0"/>
        <he index="1634" x="506.75" y="915.5"/>
        <he index="1635" x="666.25" y="1380.5"/>
        <he index="1636" x="165.75" y="565.0"/>
        <he index="1637" x="356.75" y="1531.5"/>
        <he index="1638" x="359.75" y="1242.0"/>
        <he index="1639" x="807.75" y="618.5"/>
        <he index="1640" x="81.25" y="1530.0"/>
        <he index="1641" x="331.75" y="99.0"/>
        <he index="1642" x="731.75" y="472.5"/>
        <he index="1643" x="657.25" y="888.0"/>
        <he index="1644" x="918.25" y="364.5"/>
        <he index="1645" x="592.25" y="360.0"/>
        <he index="1646" x="222.75" y="1152.0"/>
        <he index="1647" x="331.25" y="778.0"/>
        <he index="1648" x="346.25" y="830.5"/>
        <he index="1649" x="582.25" y="904.0"/>
        <he index="1650" x="690.75" y="622.0"/>
        <he index="1651" x="644.25" y="357.5"/>
        <he index="1652" x="521.75" y="423.0"/>
        <he index="1653" x="297.75" y="529.0"/>
        <he index="1654" x="497.75" y="417.5"/>
        <he index="1655" x="655.75" y="573.5"/>
        <he index="1656" x="183.75" y="448.0"/>
        <he index="1657" x="142.75" y="976.5"/>
        <he index="1658" x="896.25" y="758.0"/>
        <he index="1659" x="526.75" y="265.5"/>
        <he index="1660" x="547.25" y="493.5"/>
        <he index="1661" x="945.25" y="514.0"/>
        <he index="1662" x="627.25" y="500.5"/>
        <he index="1663" x="361.25" y="70.0"/>
        <he index="1664" x="156.25" y="531.5"/>
        <he index="1665" x="940.75" y="633.0"/>
        <he index="1666" x="453.25" y="1082.5"/>
        <he index="1667" x="778.25" y="1179.5"/>
        <he index="1668" x="166.75" y="650.0"/>
        <he index="1669" x="764.25" y="362.5"/>
        <he index="1670" x="859.75" y="352.5"/>
        <he index="1671" x="269.75" y="402.5"/>
        <he index="1672" x="45.75" y="1372.0"/>
        <he index="1673" x="120.25" y="278.5"/>
        <he index="1674" x="141.25" y="1325.5"/>
        <he index="1675" x="303.25" y="1502.0"/>
        <he index="1676" x="412.75" y="865.0"/>
        <he index="1677" x="548.75" y="713.5"/>
        <he index="1678" x="17.25" y="453.5"/>
        <he index="1679" x="290.75" y="723.5"/>
        <he index="1680" x="17.25" y="1452.0"/>
        <he index="1681" x="1048.75" y="611.0"/>
        <he index="1682" x="750.25" y="391.0"/>
        <he index="1683" x="941.25" y="701.5"/>
        <he index="1684" x="623.75" y="766.0"/>
        <he index="1685" x="448.25" y="665.5"/>
        <he index="1686" x="675.25" y="799.5"/>
        <he index="1687" x="146.25" y="552.5"/>
        <he index="1688" x="665.25" y="262.5"/>
        <he index="1689" x="555.25" y="955.0"/>
        <he index="1690" x="374.25" y="786.0"/>
        <he index="1691" x="289.25" y="1178.5"/>
        <he index="1692" x="688.75" y="1324.5"/>
        <he index="1693" x="383.75" y="1066.5"/>
        <he index="1694" x="59.25" y="319.0"/>
        <he index="1695" x="102.75" y="751.0"/>
        <he index="1696" x="645.75" y="64.0"/>
        <he index="1697" x="607.25" y="1450.5"/>
        <he index="1698" x="42.25" y="1212.5"/>
        <he index="1699" x="16.75" y="410.5"/>
        <he index="1700" x="361.75" y="322.0"/>
        <he index="1701" x="934.75" y="774.5"/>
        <he index="1702" x="262.25" y="617.5"/>
        <he index="1703" x="631.25" y="336.0"/>
        <he index="1704" x="885.25" y="708.5"/>
        <he index="1705" x="391.75" y="518.0"/>
        <he index="1706" x="558.25" y="280.0"/>
        <he index="1707" x="527.25" y="379.0"/>
        <he index="1708" x="235.75" y="111.0"/>
        <he index="1709" x="106.75" y="579.0"/>
        <he index="1710" x="77.25" y="583.5"/>
        <he index="1711" x="67.25" y="1211.0"/>
        <he index="1712" x="372.25" y="175.0"/>
        <he index="1713" x="506.75" y="225.5"/>
        <he index="1714" x="408.75" y="199.0"/>
        <he index="1715" x="384.75" y="1276.5"/>
        <he index="1716" x="156.75" y="234.0"/>
        <he index="1717" x="17.25" y="1372.5"/>
        <he index="1718" x="682.75" y="212.0"/>
        <he index="1719" x="285.75" y="914.5"/>
        <he index="1720" x="59.25" y="186.0"/>
        <he index="1721" x="16.75" y="324.0"/>
        <he index="1722" x="539.25" y="238.0"/>
        <he index="1723" x="141.25" y="340.0"/>
        <he index="1724" x="16.75" y="367.0"/>
        <he index="1725" x="362.75" y="887.0"/>
        <he index="1726" x="232.75" y="285.5"/>
        <he index="1727" x="289.75" y="431.0"/>
        <he index="1728" x="124.25" y="1487.5"/>
        <he index="1729" x="902.25" y="812.5"/>
        <he index="1730" x="179.25" y="468.0"/>
        <he index="1731" x="109.25" y="683.5"/>
        <he index="1732" x="684.75" y="1281.5"/>
        <he index="1733" x="450.25" y="259.5"/>
        <he index="1734" x="255.25" y="349.5"/>
        <he index="1735" x="674.25" y="237.5"/>
        <he index="1736" x="534.75" y="287.5"/>
        <he index="1737" x="430.25" y="44.0"/>
        <he index="1738" x="17.25" y="1292.5"/>
        <he index="1739" x="545.75" y="678.5"/>
        <he index="1740" x="606.25" y="19.5"/>
        <he index="1741" x="679.25" y="834.0"/>
        <he index="1742" x="950.25" y="755.0"/>
        <he index="1743" x="181.75" y="72.5"/>
        <he index="1744" x="150.25" y="1284.0"/>
        <he index="1745" x="152.75" y="945.5"/>
        <he index="1746" x="481.75" y="436.0"/>
        <he index="1747" x="97.75" y="144.0"/>
        <he index="1748" x="353.75" y="163.5"/>
        <he index="1749" x="966.25" y="402.0"/>
        <he index="1750" x="17.25" y="280.5"/>
        <he index="1751" x="894.75" y="95.0"/>
        <he index="1752" x="110.75" y="1128.0"/>
        <he index="1753" x="639.75" y="267.0"/>
        <he index="1754" x="94.75" y="894.5"/>
        <he index="1755" x="299.25" y="127.0"/>
        <he index="1756" x="344.75" y="340.0"/>
        <he index="1757" x="545.75" y="1303.5"/>
        <he index="1758" x="175.25" y="625.0"/>
        <he index="1759" x="190.75" y="207.5"/>
        <he index="1760" x="17.25" y="151.0"/>
        <he index="1761" x="17.25" y="1213.0"/>
        <he index="1762" x="591.25" y="318.0"/>
        <he index="1763" x="588.25" y="33.5"/>
        <he index="1764" x="31.25" y="1571.5"/>
        <he index="1765" x="847.75" y="812.0"/>
        <he index="1766" x="565.75" y="568.5"/>
        <he index="1767" x="16.75" y="623.5"/>
        <he index="1768" x="211.75" y="246.5"/>
        <he index="1769" x="49.25" y="622.0"/>
        <he index="1770" x="911.75" y="739.5"/>
        <he index="1771" x="572.25" y="202.0"/>
        <he index="1772" x="274.25" y="362.5"/>
        <he index="1773" x="317.25" y="139.0"/>
        <he index="1774" x="576.25" y="123.5"/>
        <he index="1775" x="550.75" y="210.0"/>
        <he index="1776" x="482.75" y="35.0"/>
        <he index="1777" x="507.25" y="113.0"/>
        <he index="1778" x="620.75" y="65.5"/>
        <he index="1779" x="172.25" y="489.5"/>
        <he index="1780" x="253.75" y="324.0"/>
        <he index="1781" x="130.75" y="115.0"/>
        <he index="1782" x="56.25" y="498.0"/>
        <he index="1783" x="472.75" y="255.5"/>
        <he index="1784" x="310.25" y="236.0"/>
        <he index="1785" x="16.75" y="483.0"/>
        <he index="1786" x="271.75" y="134.5"/>
        <he index="1787" x="101.25" y="544.0"/>
        <he index="1788" x="377.75" y="303.5"/>
        <he index="1789" x="167.25" y="139.0"/>
        <he index="1790" x="517.75" y="199.0"/>
        <he index="1791" x="253.75" y="122.5"/>
        <he index="1792" x="601.25" y="81.5"/>
        <he index="1793" x="273.75" y="212.5"/>
        <he index="1794" x="141.75" y="56.0"/>
        <he index="1795" x="484.25" y="188.5"/>
        <he index="1796" x="93.25" y="599.5"/>
        <he index="1797" x="376.75" y="254.5"/>
        <he index="1798" x="596.25" y="112.0"/>
        <he index="1799" x="326.25" y="170.5"/>
        <he index="1800" x="527.25" y="172.5"/>
        <he index="1801" x="589.75" y="142.5"/>
        <he index="1802" x="493.25" y="163.5"/>
        <he index="1803" x="400.25" y="303.5"/>
        <he index="1804" x="172.25" y="195.5"/>
        <he index="1805" x="569.75" y="49.0"/>
        <he index="1806" x="414.75" y="282.5"/>
        <he index="1807" x="146.75" y="497.5"/>
        <he index="1808" x="251.75" y="298.0"/>
        <he index="1809" x="581.75" y="172.5"/>
        <he index="1810" x="16.75" y="588.0"/>
        <he index="1811" x="196.25" y="136.0"/>
        <he index="1812" x="193.25" y="234.0"/>
        <he index="1813" x="153.75" y="183.0"/>
        <he index="1814" x="515.75" y="61.0"/>
        <he index="1815" x="390.25" y="187.0"/>
        <he index="1816" x="217.25" y="98.5"/>
        <he index="1817" x="534.75" y="47.5"/>
        <he index="1818" x="16.75" y="553.0"/>
        <he index="1819" x="112.25" y="524.5"/>
        <he index="1820" x="472.25" y="107.5"/>
        <he index="1821" x="477.25" y="83.5"/>
        <he index="1822" x="92.75" y="121.0"/>
        <he index="1823" x="16.75" y="518.0"/>
        <he index="1824" x="450.75" y="177.5"/>
        <he index="1825" x="398.75" y="218.0"/>
        <he index="1826" x="428.75" y="261.5"/>
        <he index="1827" x="288.75" y="323.0"/>
        <he index="1828" x="441.25" y="200.0"/>
        <he index="1829" x="230.25" y="259.0"/>
        <he index="1830" x="47.25" y="586.5"/>
        <he index="1831" x="473.75" y="212.5"/>
        <he index="1832" x="344.75" y="182.0"/>
        <he index="1833" x="191.25" y="103.0"/>
        <he index="1834" x="307.25" y="335.0"/>
        <he index="1835" x="548.25" y="163.5"/>
        <he index="1836" x="248.75" y="271.5"/>
        <he index="1837" x="133.25" y="143.0"/>
        <he index="1838" x="547.25" y="90.0"/>
        <he index="1839" x="441.25" y="239.0"/>
        <he index="1840" x="566.25" y="78.0"/>
        <he index="1841" x="279.75" y="165.0"/>
        <he index="1842" x="500.75" y="138.5"/>
        <he index="1843" x="285.75" y="296.0"/>
        <he index="1844" x="496.75" y="71.0"/>
        <he index="1845" x="370.25" y="224.5"/>
        <he index="1846" x="41.25" y="481.5"/>
        <he index="1847" x="297.75" y="177.0"/>
        <he index="1848" x="472.25" y="169.5"/>
        <he index="1849" x="227.25" y="232.0"/>
        <he index="1850" x="161.25" y="110.5"/>
        <he index="1851" x="340.75" y="230.5"/>
        <he index="1852" x="225.75" y="129.5"/>
        <he index="1853" x="362.75" y="194.0"/>
        <he index="1854" x="143.75" y="98.0"/>
        <he index="1855" x="555.75" y="135.5"/>
        <he index="1856" x="346.25" y="260.0"/>
        <he index="1857" x="106.75" y="490.0"/>
        <he index="1858" x="527.25" y="101.5"/>
        <he index="1859" x="73.25" y="548.5"/>
        <he index="1860" x="278.75" y="241.0"/>
        <he index="1861" x="282.75" y="268.5"/>
        <he index="1862" x="337.25" y="305.0"/>
        <he index="1863" x="255.75" y="200.5"/>
        <he index="1864" x="250.25" y="171.5"/>
        <he index="1865" x="152.75" y="154.5"/>
        <he index="1866" x="205.75" y="193.0"/>
        <he index="1867" x="81.75" y="494.5"/>
        <he index="1868" x="364.25" y="272.0"/>
        <he index="1869" x="521.25" y="128.5"/>
        <he index="1870" x="224.25" y="205.0"/>
        <he index="1871" x="322.75" y="219.0"/>
        <he index="1872" x="480.25" y="145.5"/>
        <he index="1873" x="201.75" y="164.5"/>
        <he index="1874" x="260.25" y="229.0"/>
        <he index="1875" x="314.75" y="264.5"/>
        <he index="1876" x="318.75" y="293.0"/>
        <he index="1877" x="45.25" y="551.5"/>
        <he index="1878" x="232.75" y="159.5"/>
        <he index="1879" x="304.75" y="207.0"/>
        <he index="1880" x="121.75" y="92.0"/>
        <he index="1881" x="183.75" y="153.0"/>
        <he index="1882" x="69.75" y="514.0"/>
        <he index="1883" x="43.25" y="516.5"/>
    </root>
